Workbook

Sheet Content
O5: Content
O6: General Definitions
O7: Key Figures Yearly
O8: Key Figures Quarterly
O9: Calc Key Figures
O10: Volume Quarterly
O11: Volume Monthly
O12: Revenue and EBIT walk
O13: Income Statement
O14: Revenue Geographical
O15: BS - Assets
O16: BS - Equity & Liabilities
O17: Cash Flow

Sheet General Definitions
A1: General Definitions
A10: Key word | B10: Description
A11: Volvo Car Group and Volvo Cars | B11: Volvo Car Group and Volvo Cars refers to Volvo Car AB (publ.), Volvo Car Corporation and all its subsidiaries. Volvo Car AB (publ.), with its registered office in Gothenburg, is a publicly listed company on the Nasdaq Stockholm Stock Exchange. The largest owner, holding 78.65% of shares and capital, is Geely Sweden Holdings AB, owned by Shanghai Geely Zhaoyuan International Investment Co., Ltd., registered in Shanghai, China, ultimately owned by Zhejiang Geely Holding Group Ltd., registered in Hangzhou, China. The remaining 18% of the shares are held by Nordic and international institutions as well as retail investors. Volvo Car AB (publ.) holds shares in its subsidiary Volvo Car Corporation and provides the Group with certain financing solutions. Volvo Car AB (publ.), indirectly through Volvo Car Corporation and its subsidiaries, operates in the automotive industry with business relating to the design, development, manufacturing, marketing and sales of cars and thereto related services. Volvo Car Group and its global operations are referred to as “Volvo Cars”.
A12: Asscoiated companies | B12: Associated companies are companies in which Volvo Car Group has a significant but not controlling influence, which generally is when Volvo Car Group holds between 20% and 50% of the shares.
A13: Joint venture companies (JVs) | B13: Joint ventures refer to companies in which Volvo Car Group, through contractual cooperation together with one or more parties, has joint control over the operational and financial management and has rights to the net assets of the arrangement.
A14: Retail sales | B14: Retail sales refer to sales to end customers (including a portion of cars used as customer loaner and demo cars) and is a relevant measure of the demand for Volvo Cars from an end customer point of view.
A15: Wholesales | B15: Wholesales refer to new car sales to dealers and other customers including rentals.
A16: Europe | B16: Europe is defined as EU (European Union) + EFTA (European Free Trade Association) + UK (United Kingdom).
A17: Passenger cars | B17: Passenger cars are vehicles with at least four wheels, used for the transport of passengers, and comprising no more than eight seats in addition to the driver’s seat.
A18: Traditional premium segment | B18: Traditional premium segment is the premium market brands such as Volvo Cars, Audi, BMW, Lexus, Mercedes, Tesla and so on.
A19: Battery Electric Vehicles (BEV) | B19: BEV cars include all vehicles which are 100% fully electrified cars.
A20: Non Battery Electric Vehicles (Non-BEV) | B20: Non-BEV cars include all vehicles which are not 100% fully electrified cars (BEV). For Volvo Cars, it includes plug-in hybid (PHEV), mild hybrid (MHEV) and internal combustion engine cars (ICE).
A21: Electrified cars | B21: Electrified cars include 100% fully electric cars, the same as the Battery Electric Vehicles (BEV), and Plug-in hybrids (PHEV), in both petrol and diesel with cord for charging.
... A38: Shares of investing cash flow | B38: Share of investing Cash Flow is defined as the share of investing cash flow allocated to certain types of development as a percentage of the total investing cash flow. Share of investing cash flow presents the allocation the Group’s cash resources to certain investments during the reporting period.

Sheet Key Figures Yearly
D1: Key Figures Yearly
E9: Full Year 20121) | F9: Full Year 20131) | G9: Full Year 20142) | H9: Full Year 20153)4)5)6) | I9: Full Year 20163)4)5)6) | J9: Full Year 20174)5)6) | K9: Full year 20186) | L9: Full year 2019 | M9: Full year 20207)9) | N9: Full year 20217)8)9) | O9: Full year 2022 | P9: Full year 2023 | Q9: Full year 2024
D10: Retail sales, units | E10: 421951 | F10: 427840 | G10: 465866 | H10: 503127 | I10: 534332 | J10: 571577 | K10: 642253 | L10: 705452 | M10: 661713 | N10: 698693 | O10: 615121 | P10: 708716 | Q10: 763389
D11: Revenue, MSEK | E11: 124547 | F11: 122245 | G11: 137590 | H11: 160515 | I11: 178586 | J11: 208646 | K11: 252653 | L11: 274117 | M11: 262833 | N11: 282045 | O11: 330145 | P11: 399343 | Q11: 400234
D12: Revenue per new car, BEV (SEKk) 10) | E12: ND | F12: ND | G12: ND | H12: ND | I12: ND | J12: ND | K12: ND | L12: ND | M12: ND | N12: 430169 | O12: 448820 | P12: 465386 | Q12: ND
D13: Revenue per new car, non-BEV (SEKk) 10) | E13: ND | F13: ND | G13: ND | H13: ND | I13: ND | J13: ND | K13: ND | L13: ND | M13: ND | N13: 356568 | O13: 415179 | P13: 440375 | Q13: ND
D14: Research and development expenses, MSEK | E14: -6289 | F14: -5864 | G14: -7193 | H14: -9480 | I14: -10174 | J14: -10187 | K14: -10903 | L14: -11446 | M14: -11362 | N14: -12714 | O14: -11514 | P14: -12884 | Q14: -16983
D15: Operating income (EBIT), MSEK | E15: 66 | F15: 1919 | G15: 2128 | H15: 6620 | I15: 11014 | J15: 14061 | K15: 14185 | L15: 14303 | M15: 8036 | N15: 20275 | O15: 22332 | P15: 19939 | Q15: 22318
D16: Operating income (EBIT) excl. share of income from JVs & associates, MSEK | E16: -6 | F16: 1740 | G16: 1937 | H16: 6390 | I16: 10596 | J16: 13861 | K16: 14118 | L16: 14471 | M16: 8388 | N16: 21226 | O16: 17889 | P16: 25567 | Q16: 27040
D17: Net income, MSEK | E17: -542 | F17: 960 | G17: 508 | H17: 4476 | I17: 7460 | J17: 10225 | K17: 9781 | L17: 9603 | M17: 7308 | N17: 14177 | O17: 17003 | P17: 14066 | Q17: 15934
D18: Basic earnings per share, SEK | E18: N/A | F18: N/A | G18: N/A | H18: N/A | I18: N/A | J18: N/A | K18: N/A | L18: N/A | M18: 2.19 | N18: 4.72 | O18: 5.23 | P18: 4.38 | Q18: 5.17
D19: EBITDA, MSEK | E19: 8082 | F19: 9057 | G19: 9491 | H19: 16019 | I19: 21541 | J19: 26159 | K19: 27398 | L19: 29851 | M19: 22578 | N19: 35280 | O19: 38423 | P19: 37388 | Q19: 45048
D20: Gross income per new car, BEV (SEKk) 10) | E20: ND | F20: ND | G20: ND | H20: ND | I20: ND | J20: ND | K20: ND | L20: ND | M20: ND | N20: 57277 | O20: 36758 | P20: 40269 | Q20: ND
D21: Gross income per new car, non-BEV (SEKk) 10) | E21: ND | F21: ND | G21: ND | H21: ND | I21: ND | J21: ND | K21: ND | L21: ND | M21: ND | N21: 68723 | O21: 88865 | P21: 102898 | Q21: ND
D22: Cash flow from operating activities, MSEK | E22: 2749 | F22: 8861 | G22: 8839 | H22: 23140 | I22: 27287 | J22: 24933 | K22: 26765 | L22: 32374 | M22: 34890 | N22: 29852 | O22: 33658 | P22: 42867 | Q22: 47372
D23: Cash flow from investing activities, MSEK | E23: -7678 | F23: -8752 | G23: -13605 | H23: -15906 | I23: -20772 | J23: -28733 | K23: -22060 | L23: -20801 | M23: -21608 | N23: -34737 | O23: -39552 | P23: -51842 | Q23: -46245
D24: Net cash, MSEK | E24: 2240 | F24: 2607 | G24: 856 | H24: 7721 | I24: 18873 | J24: 12513 | K24: 18029 | L24: 25214 | M24: 35241 | N24: 44846 | O24: 38061 | P24: 27487 | Q24: 27115
D25: Gross margin, % | E25: 16 | F25: 16.6 | G25: 17.1 | H25: 21.8 | I25: 21.7 | J25: 22.4 | K25: 19.5 | L25: 19 | M25: 17.5 | N25: 21.6 | O25: 18.3 | P25: 19.4 | Q25: 19.8
D26: Gross margin BEV, % 10) | E26: ND | F26: ND | G26: ND | H26: ND | I26: ND | J26: ND | K26: ND | L26: ND | M26: ND | N26: 13.3 | O26: 8.2 | P26: 8.7 | Q26: ND
D27: Gross margin Non-BEV, % 10) | E27: ND | F27: ND | G27: ND | H27: ND | I27: ND | J27: ND | K27: ND | L27: ND | M27: ND | N27: 19.3 | O27: 21.4 | P27: 23.4 | Q27: ND
D28: EBIT margin, % | E28: 0.1 | F28: 1.6 | G28: 1.5 | H28: 4.1 | I28: 6.2 | J28: 6.7 | K28: 5.6 | L28: 5.2 | M28: 3.1 | N28: 7.2 | O28: 6.8 | P28: 5 | Q28: 5.6
D29: EBIT margin excl. share of income from JVs & associates, % | E29: 0 | F29: 1.4 | G29: 1.4 | H29: 4 | I29: 5.9 | J29: 6.6 | K29: 5.6 | L29: 5.3 | M29: 3.2 | N29: 7.5 | O29: 5.4 | P29: 6.4 | Q29: 6.8
D30: EBITDA margin, % | E30: 6.5 | F30: 7.4 | G30: 6.9 | H30: 10 | I30: 12.1 | J30: 12.5 | K30: 10.8 | L30: 10.9 | M30: 8.6 | N30: 12.5 | O30: 11.6 | P30: 9.4 | Q30: 11.3
D31: Equity ratio % | E31: ND | F31: ND | G31: ND | H31: ND | I31: ND | J31: ND | K31: ND | L31: ND | M31: ND | N31: 33.4 | O31: 35.4 | P31: 36.6 | Q31: 36.6
D32: Share of investing cash flow BEV, % 10) | E32: ND | F32: ND | G32: ND | H32: ND | I32: ND | J32: ND | K32: ND | L32: ND | M32: ND | N32: 53.6 | O32: 68.5 | P32: 68.4 | Q32: ND
D33: Share of investing cash flow non-BEV, % 10) | E33: ND | F33: ND | G33: ND | H33: ND | I33: ND | J33: ND | K33: ND | L33: ND | M33: ND | N33: 12.9 | O33: 6.2 | P33: 5.9 | Q33: ND
D34: Return on invested capital, ROIC, %9) | E34: ND | F34: 4.2 | G34: 3.8 | H34: 10.6 | I34: 18.2 | J34: 19.4 | K34: 16.1 | L34: 14.5 | M34: 7.9 | N34: 18.6 | O34: 16.7 | P34: 12.4 | Q34: 12
D36: ND = Not disclosed
D37: Items affecting comparability, MSEK | E37: Full Year 2012 | F37: Full Year 2013* | G37: Full Year 2014** | H37: Full Year 2015*** | I37: Full Year 2016*** | J37: Full Year 2017*** | K37: Full year 2018 | L37: Full year 2019 | M37: Full year RESTATE 2020 | N37: Full year 2021 | O37: Full year 2022 | P37: Full year 2023 | Q37: Full year 2024
D38: Whereof affecting JVs & associates
D39: de-SPAC listing of Polestar, net effect | E39: - | F39: - | G39: - | H39: - | I39: - | J39: - | K39: - | L39: - | M39: - | N39: - | O39: 5899 | P39: - | Q39: -
D40: Share of income, Zenuity | E40: - | F40: - | G40: - | H40: - | I40: - | J40: - | K40: - | L40: - | M40: 672 | N40: 1175 | O40: - | P40: - | Q40: -
D41: Valuation effect in connection with the private placement in Polestar Automotive Holding Ltd | E41: - | F41: - | G41: - | H41: - | I41: - | J41: - | K41: - | L41: - | M41: - | N41: 2039 | O41: - | P41: - | Q41: -
D42: Impairment of JV-shareholding in NOVO Energy AB | J42: - | K42: - | L42: - | M42: - | N42: - | O42: - | P42: - | Q42: -1702
D43: Subtotal | E43: - | F43: - | G43: - | H43: - | I43: - | J43: - | K43: - | L43: - | M43: 672 | N43: 3214 | O43: =+O39 -> 5899 | P43: - | Q43: -
D44: Whereof affecting Volvo Cars operations
D45: Restructuring costs | E45: - | F45: - | G45: - | H45: - | I45: - | J45: - | K45: - | L45: - | M45: - | N45: - | O45: - | P45: -624 | Q45: -
D46: Governmental support related to Covid-19 | E46: - | F46: - | G46: - | H46: - | I46: - | J46: - | K46: - | L46: - | M46: 1013 | N46: 66 | O46: - | P46: - | Q46: -
D47: Subtotal | E47: - | F47: - | G47: - | H47: - | I47: - | J47: - | K47: - | L47: - | M47: 1013 | N47: 66 | O47: - | P47: - | Q47: -
D48: Total | E48: - | F48: - | G48: - | H48: - | I48: - | J48: - | K48: - | L48: - | M48: 1685 | N48: 3280 | O48: 5899 | P48: -624 | Q48: -
D50: 1) Not restated after the acquisitions of the Chinese industrial entities in 2015.
D51: 2) The comparative figures for 2014 are restated to include the new Volvo Car Group structure including the acquired Chinese industrial entities. For further descriptions refer to the Volvo Car Group’s annual report 2015.
D52: 3)2015 and 2016 year's net revenue has been restated to hedged currency rates.
D53: 4) In 2017, sold licenses have been reclassified from Other Operating Income to Net Revenue. The comparative periods (2015 and 2016) has been restated.
D54: 5) In 2017, costs have been reclassified from cost of sales to research and development. The comparative periods (2015 and 2016) has been restated.
D55: 6) 2018 there has been a change related to sale of certain cars accounted for as operating leasing. The comparative periods 2017, 2016 and 2015 have been changed accordingly, reducing net revenue and cost of sales. The change has not had any effect on gross income.
D56: 7) In 2021, Dividends received from joint ventures and associates were reclassified from Investing to Operating activities and the comparative figures for 2020 have been adjusted accordingly.
D57: 8) In 2022, there has been a change in the elimination of internal profit related to sale of digital services from VCC to other entities within the Group. This change has resulted in a decrease of cost of sales, research and development expenses and selling expenses against an increase of administrative expenses. The comparative figures have been adjusted accordingly, but only for 2021, due to the reclassification for previous periods not having a material impact. The reclassification has no impact on EBIT.
D58: 9) In 2022, a prior period error was identified with regards to the recognition of a government grant in China. The comparative figures have been adjusted accordingly affecting 2020 and 2021.
D60: 10) The second quarter report 2024 is the last quarter where this information is presented.

Sheet Key Figures Quarterly
D1: Key Figures Quarterly
E9: Q1 2020 | F9: Q2 2020 | G9: Q3 2020 | H9: Q4 2020 | I9: Q1 20211) | J9: Q2 20211) | K9: Q3 20211) | L9: Q4 20211) | M9: Q1 2022 | N9: Q2 2022 | O9: Q3 2022 | P9: Q4 2022 | Q9: Q1 2023 | R9: Q2 2023 | S9: Q3 2023 | T9: Q4 2023 | U9: Q1 2024 | V9: Q2 2024 | W9: Q3 2024 | X9: Q4 2024
D10: Retail sales, units | E10: 131889 | F10: 138073 | G10: 181166 | H10: 210585 | I10: 185698 | J10: 195059 | K10: 149892 | L10: 168044 | M10: 148295 | N10: 143006 | O10: 137686 | P10: 186134 | Q10: 162938 | R10: 178753 | S10: 167467 | T10: 199558 | U10: 182687 | V10: 205386 | W10: 172849 | X10: 202467
D11: Revenue, MSEK | E11: 56517 | F11: 55242 | G11: 65763 | H11: 85311 | I11: 68593 | J11: 72538 | K11: 60838 | L11: 80076 | M11: 74269 | N11: 71300 | O11: 79329 | P11: 105247 | Q11: 95705 | R11: 102152 | S11: 92045 | T11: 109441 | U11: 93878 | V11: 101454 | W11: 92783 | X11: 112119
D12: Revenue per new car, BEV (SEKk) 2) | E12: ND | F12: ND | G12: ND | H12: ND | I12: ND | J12: ND | K12: ND | L12: ND | M12: 435895 | N12: 469086 | O12: 427436 | P12: 457510 | Q12: 456337 | R12: 430275 | S12: 494217 | T12: 463892 | U12: 416027 | V12: 407654 | W12: ND | X12: ND
D13: Revenue per new car, non-BEV (SEKk) 2) | E13: ND | F13: ND | G13: ND | H13: ND | I13: ND | J13: ND | K13: ND | L13: ND | M13: 385743 | N13: 417393 | O13: 421234 | P13: 434401 | Q13: 446872 | R13: 416904 | S13: 432857 | T13: 440732 | U13: 428061 | V13: 442823 | W13: ND | X13: ND
D14: Research and development expenses, MSEK | E14: -2706 | F14: -3272 | G14: -3299 | H14: -2085 | I14: -3418 | J14: -3515 | K14: -2599 | L14: -3182 | M14: -3230 | N14: -2918 | O14: -2817 | P14: -2549 | Q14: -2878 | R14: -3383 | S14: -2909 | T14: -3714 | U14: -3827 | V14: -4725 | W14: -3403 | X14: -5028
D15: Operating income (EBIT), MSEK | E15: 639 | F15: -1628 | G15: 4181 | H15: 4844 | I15: 8423 | J15: 4815 | K15: 3329 | L15: 3708 | M15: 6038 | N15: 10801 | O15: 2050 | P15: 3443 | Q15: 5100 | R15: 4993 | S15: 4458 | T15: 5388 | U15: 4706 | V15: 7969 | W15: 5790 | X15: 3853
D16: Operating income (EBIT) excl. share of income from associates, MSEK | E16: 1077 | F16: -1278 | G16: =4146-387 -> 3759 | H16: 4830 | I16: 5528 | J16: 5714 | K16: 4316 | L16: 5668 | M16: 5877 | N16: 4612 | O16: 3513 | P16: 3887 | Q16: 6315 | R16: 6427 | S16: 6148 | T16: 6677 | U16: 6795 | V16: 8216 | W16: 5710 | X16: 6319
D17: Net income, MSEK | E17: 596 | F17: -1767 | G17: 2933 | H17: 5546 | I17: 6463 | J17: 3164 | K17: 2292 | L17: 2258 | M17: 4503 | N17: 8978 | O17: 665 | P17: 2857 | Q17: 3975 | R17: 3540 | S17: 3219 | T17: 3332 | U17: 3587 | V17: 5654 | W17: 4356 | X17: 2337
D18: Basic earnings per share, SEK | E18: 0.22 | F18: -0.94 | G18: 1.01 | H18: 1.9 | I18: 2.28 | J18: 0.99 | K18: 0.86 | L18: 0.66 | M18: 1.29 | N18: 3 | O18: 0.11 | P18: 0.82 | Q18: 1.21 | R18: 1.12 | S18: 1.0072078 | T18: 1.04 | U18: 1.1216556 | V18: 1.79 | W18: 1.41 | X18: 0.84166552
D19: EBITDA, MSEK | E19: 4492 | F19: 2327 | G19: =3649+4181 -> 7830 | H19: =+'Cash Flow'!V11+'Cash Flow'!V12 -> 7929 | I19: 12557 | J19: 8361 | K19: 6937 | L19: 7425 | M19: 10023 | N19: 14821 | O19: 6055 | P19: 7524 | Q19: 9229 | R19: 9198 | S19: 8651 | T19: 10310 | U19: 10124 | V19: 13944 | W19: 10369 | X19: 10611
D20: Gross income per new car, BEV (SEKk) 2) | E20: ND | F20: ND | G20: ND | H20: ND | I20: ND | J20: ND | K20: ND | L20: ND | M20: 58950 | N20: 70660 | O20: 21104 | P20: 29102 | Q20: 33948 | R20: 11084 | S20: 46408 | T20: 62347 | U20: 67083 | V20: 81523 | W20: ND | X20: ND
D21: Gross income per new car, non-BEV (SEKk) 2) | E21: ND | F21: ND | G21: ND | H21: ND | I21: ND | J21: ND | K21: ND | L21: ND | M21: 81500 | N21: 93357 | O21: 83223 | P21: 96369 | Q21: 104190 | R21: 89158 | S21: 96865 | T21: 115162 | U21: 107011 | V21: 101816 | W21: ND | X21: ND
D22: Cash flow from operating activities, MSEK | E22: -9880 | F22: 6407 | G22: =+'Cash Flow'!U30 -> 16394 | H22: =+'Cash Flow'!V30 -> 21962 | I22: -4188 | J22: 6521 | K22: -1886 | L22: 29405 | M22: -4239 | N22: 7371 | O22: 13400 | P22: 16961 | Q22: -2380 | R22: 16983 | S22: 10124 | T22: 18140 | U22: -937 | V22: 12779 | W22: 9212 | X22: 26318
D23: Cash flow from investing activities, MSEK | E23: -5514 | F23: -3816 | G23: =+'Cash Flow'!U45 -> -6246.329 | H23: =+'Cash Flow'!V45 -> -6024.671 | I23: -2702 | J23: -6530 | K23: -7341 | L23: -18164 | M23: -8033 | N23: -12971 | O23: -10163 | P23: -8385 | Q23: -15069 | R23: 16299 | S23: -8395 | T23: -12079 | U23: -11264 | V23: -12660 | W23: -9613 | X23: -12708
D24: Gross margin, % | E24: 17.3 | F24: 13.6 | G24: 19.5 | H24: 18.5 | I24: 20.6 | J24: 22.3 | K24: 22.7 | L24: 20.8 | M24: 21.2 | N24: 19.8 | O24: 17.3 | P24: 16 | Q24: 17.9 | R24: 19 | S24: 19.6 | T24: 20.9 | U24: 19.3 | V24: 22.8 | W24: 20.5 | X24: 17.1
D25: Gross margin BEV, % 2) | E25: ND | F25: ND | G25: ND | H25: ND | I25: ND | J25: ND | K25: ND | L25: ND | M25: 13.5 | N25: 15.1 | O25: 4.9 | P25: 6.4 | Q25: 7.4 | R25: 2.6 | S25: 9.4 | T25: 13.4 | U25: 16.1 | V25: 20 | W25: ND | X25: ND
D26: Gross margin Non-BEV, % 2) | E26: ND | F26: ND | G26: ND | H26: ND | I26: ND | J26: ND | K26: ND | L26: ND | M26: 21.1 | N26: 22.4 | O26: 19.8 | P26: 22.2 | Q26: 23.3 | R26: 21.4 | S26: 22.4 | T26: 26.1 | U26: 25 | V26: 23 | W26: ND | X26: ND
D27: EBIT margin, % | E27: 1.1 | F27: -2.9 | G27: 6.4 | H27: 5.7 | I27: 12.3 | J27: 6.6 | K27: 5.5 | L27: 4.6 | M27: 8.1 | N27: 15.1 | O27: 2.6 | P27: 3.3 | Q27: 5.3 | R27: 4.9 | S27: 4.8 | T27: 4.9 | U27: 5 | V27: 7.9 | W27: 6.2 | X27: 3.4
D28: EBIT margin excl. Share of income from JV & associates, % | E28: 1.9 | F28: -2.3 | G28: 5.7 | H28: 5.7 | I28: 8.1 | J28: 7.9 | K28: 7.1 | L28: 7.1 | M28: 7.9 | N28: 6.5 | O28: 4.4 | P28: 3.7 | Q28: 6.6 | R28: 6.3 | S28: 6.7 | T28: 6.1 | U28: 7.2 | V28: 8.1 | W28: 6.2 | X28: 5.6
D29: EBITDA margin, % | E29: 7.9 | F29: 4.2 | G29: 11.9 | H29: 9.3 | I29: 18.3 | J29: 11.5 | K29: 11.4 | L29: 9.3 | M29: 13.5 | N29: 20.8 | O29: 7.6 | P29: 7.1 | Q29: 9.6 | R29: 9 | S29: 9.4 | T29: 9.4 | U29: 10.8 | V29: 13.7 | W29: 11.2 | X29: 9.5
D30: Share of investing cash flow BEV, % 2) | E30: ND | F30: ND | G30: ND | H30: ND | I30: ND | J30: ND | K30: ND | L30: ND | M30: 57.3 | N30: 69.9 | O30: 63.4 | P30: 75.2 | Q30: 74.8 | R30: 64.6 | S30: 67.4 | T30: 67.7 | U30: 68.1 | V30: 70.1 | W30: ND | X30: ND
D31: Share of investing cash flow non-BEV, % 2) | E31: ND | F31: ND | G31: ND | H31: ND | I31: ND | J31: ND | K31: ND | L31: ND | M31: 9.3 | N31: 8.5 | O31: 8.1 | P31: 2.5 | Q31: 6.4 | R31: 6.9 | S31: 4.6 | T31: 5.4 | U31: 8.2 | V31: 6.3 | W31: ND | X31: ND
D34: ND = Not disclosed
D35: Items affecting comparability, MSEK | E35: Q1 2020 | F35: Q2 2020 | G35: Q3 2020 | H35: Q4 2020 | I35: Q1 2021 | J35: Q2 2021 | K35: Q3 2021 | L35: Q4 2021 | M35: Q1 2022 | N35: Q2 2022 | O35: Q3 2022 | P35: Q4 2022 | Q35: Q1 2023 | R35: Q2 2023 | S35: Q3 2023 | T35: Q4 2023 | U35: Q1 2024 | V35: Q2 2024 | W35: Q3 2024 | X35: Q4 2024
D36: Where of affecting JVs & associates | O36: - | P36: - | Q36: - | R36: - | S36: - | T36: - | U36: - | V36: - | W36: - | X36: -
D37: de-SPAC listing of Polestar, net effect | E37: - | F37: - | G37: - | H37: - | I37: - | J37: - | K37: - | L37: - | M37: - | N37: 5899 | O37: - | P37: - | Q37: - | R37: - | S37: - | T37: - | U37: - | V37: - | W37: - | X37: -
D38: Share of income, Zenuity | E38: - | F38: - | G38: 672 | H38: - | I38: 1175 | J38: - | K38: - | L38: - | M38: - | N38: - | O38: - | P38: - | Q38: - | R38: - | S38: - | T38: - | U38: - | V38: - | W38: - | X38: -
D39: Valuation effect from the private placement in Polestar Automotive Holding Ltd | E39: - | F39: - | G39: - | H39: - | I39: 2039 | J39: - | K39: - | L39: - | M39: - | N39: - | O39: - | P39: - | Q39: - | R39: - | S39: - | T39: - | U39: - | V39: - | W39: - | X39: -
D40: Impairment of JV-shareholding in NOVO Energy AB | O40: - | P40: - | Q40: - | R40: - | S40: - | T40: - | U40: - | V40: - | W40: - | X40: -1702
D41: Subtotal | E41: - | F41: - | G41: =SUM(G36:G39) -> 672 | H41: - | I41: =SUM(I36:I39) -> 3214 | J41: - | K41: - | L41: - | M41: - | N41: - | O41: - | P41: - | Q41: - | R41: - | S41: - | T41: - | U41: - | V41: - | W41: - | X41: -
D42: Where of affecting Volvo Cars operations | O42: - | P42: - | Q42: - | R42: - | S42: - | T42: - | U42: - | V42: - | W42: - | X42: -
D43: Restructuring costs | E43: - | F43: - | G43: - | H43: - | I43: - | J43: - | K43: - | L43: - | M43: - | N43: - | O43: - | P43: - | Q43: - | R43: -880 | S43: 256 | T43: - | U43: - | V43: - | W43: - | X43: -
D44: Governmental support related to Covid-19 | E44: - | F44: 1074 | G44: - | H44: -61 | I44: 55 | J44: 11 | K44: - | L44: - | M44: - | N44: - | O44: - | P44: - | Q44: - | R44: - | S44: - | T44: - | U44: - | V44: - | W44: - | X44: -
D45: Subtotal | E45: - | F45: 1074 | G45: - | H45: -61 | I45: 55 | J45: 11 | K45: - | L45: - | M45: - | N45: - | O45: - | P45: - | Q45: - | R45: - | S45: - | T45: - | U45: - | V45: - | W45: - | X45: -
D46: Total | E46: - | F46: 1074 | G46: 672 | H46: -61 | I46: =I45+I41 -> 3269 | J46: 11 | K46: - | L46: - | M46: - | N46: 5899 | O46: - | P46: - | Q46: - | R46: -880 | S46: 256 | T46: - | U46: - | V46: - | W46: - | X46: -
D48: 1) In 2022, there has been a change in the elimination of internal profit related to sale of digital services from VCC to other entities within the Group. This change has resulted in a decrease of cost of sales, research and development expenses and selling expenses against an increase of administrative expenses. The comparative figures have been adjusted accordingly, but only for 2021, due to the reclassification for previous periods not having a material impact. The reclassification has no impact on EBIT.
D50: 2) The second quarter report 2024 is the last quarter where this information is presented.

Sheet Calc Key Figures
D1: Calculations for Key Figures
D10: Gross margin, % | E10: Q4 2024 | F10: Q4 2023 | G10: Full year 2024
D11: Gross income | E11: 19122 | F11: 22832 | G11: 79413
D12: Revenue | E12: 112119 | F12: 109441 | G12: 400234
D13: Gross margin | E13: 0.17055093 | F13: 0.20862382 | G13: 0.19841643
D16: Operating income, EBIT/EBIT margin, % | E16: Q4 2024 | F16: Q4 2023 | G16: Full year 2024
D17: Operating income, EBIT | E17: 3853 | F17: 5388 | G17: 22318
D18: Revenue | E18: 112119 | F18: 109441 | G18: 400234
D19: EBIT margin | E19: 0.034365273 | F19: 0.049232006 | G19: 0.055762379
D22: EBIT -and EBIT margin excl Share of income from JV & Associates, % | E22: Q4 2024 | F22: Q4 2023 | G22: Full year 2024
D23: EBIT excl. Share of income from JV & Associates | E23: 6319 | F23: 6677 | G23: 27040
D24: Revenue | E24: 112119 | F24: 109441 | G24: 400234
D25: EBIT margin, excl. Share of income from JV & Associates % | E25: 0.056359761 | F25: 0.061010042 | G25: 0.067560477
D28: EBITDA/EBITDA margin, % | E28: Q4 2024 | F28: Q4 2023 | G28: Full year 2024
D29: Operating income, EBIT | E29: 3853 | F29: 5388 | G29: 22318
D30: Depreciation and amortisation of non-current assets | E30: 6758 | F30: 4922 | G30: 22730
D31: EBITDA | E31: 10611 | F31: 10310 | G31: 45048
D32: Revenue | E32: 112119 | F32: 109441 | G32: 400234
D33: EBITDA margin | E33: 0.094640516 | F33: 0.094206011 | G33: 0.11255416
D37: Operating cash (SEKm) | E37: Full year 2024 | F37: Full year 2023
D38: Average two-year revenue x 10% | E38: 39978.8 | F38: 36474
D39: Operating cash | E39: 39978.8 | F39: 36474
D43: Invested capital1) (SEKm) | E43: Full year 2024 | F43: Full year 2023
D44: Total assets | E44: 372947.5 | F44: 343643
D45: Receivables on parent company | E45: — | F45: —
D46: Other long term securities holding | E46: -12409.5 | F46: -8209.5
D47: Cash and cash equivalents | E47: -52117 | F47: -55802
D48: Marketable securities | E48: -4959 | F48: -6666.5
D49: Operating cash | E49: 39978.8 | F49: 36474.4
D50: Total current liabilites | E50: -165938.5 | F50: -155187
D51: Current liabilties to parent company | E51: — | F51: —
D52: Total current interest-bearing liabilities | E52: 9055.5 | F52: 6547
D53: Total invested capital | E53: 186557.8 | F53: 160799.4
D54: 1) Calculated on two years average figures
D57: Return on invested capital, ROIC, % | E57: Full year 2024 | F57: Full year 2023
D58: EBIT (last twelve months) | E58: 22318 | F58: 19939
D59: Invested capital | E59: 186557.8 | F59: 160799.4
D60: Return on invested capital, ROIC, % | E60: 0.11963048 | F60: 0.12399922
D64: Equity ratio, % | E64: Dec 31, 2024 | F64: Dec 31, 2023
D65: Total equity | E65: 142199 | F65: 130485
D66: Total assets | E66: 388235 | F66: 356362
D67: Equity ratio, % | E67: 0.36627043 | F67: 0.36615857
D70: Net cash (SEKm) | E70: Dec 31, 2024 | F70: Dec 31, 2023
D71: Cash and cash equivalents | E71: 56373 | F71: 47861
D72: Marketable securities | E72: - | F72: 9918
D73: Liabilities to credit institutions (non-current) | E73: -3885 | F73: -4562
D74: Bonds (non-current)1) | E74: -18590 | F74: -18121
D75: Other interest-bearing non-current liabilities | E75: - | F75: -
D76: Liabilities to credit institutions (current) | E76: -1059 | F76: -937
D77: Bonds (current) | E77: -5724 | F77: -6672
D78: Net cash | E78: 27115 | F78: 27487
D80: 1) The bonds are presented above at amortised cost. The fair value risk of the EUR-denominated bonds is hedged and the bonds with fixed interest payments have been swapped into floating interest. Part of the bonds is therefore measured at fair value through the income statement and the remaining part is measured at amortised cost. On 31 December 2024 the fair value component amounted to SEK 235 (-46) m.
D82: Liquidity | E82: Dec 31, 2024 | F82: Dec 31, 2023
D83: Cash and cash equivalents | E83: 56373 | F83: 47861
D84: Undrawn credit facilities | E84: 32176 | F84: 17242
D85: Marketable securities | E85: - | F85: 9918
D86: Liquidity | E86: 88549 | F86: 75021

Sheet Volume Quarterly
D1: Volume Quarterly
D9: Unit | E9: Q1 2020 | F9: Q2 2020 | G9: Q3 2020 | H9: Q4 2020 | I9: Q1 2021 | J9: Q2 2021 | K9: Q3 2021 | L9: Q4 2021 | M9: Q1 2022 | N9: Q2 2022 | O9: Q3 2022 | P9: Q4 2022 | Q9: Q1 2023 | R9: Q2 2023 | S9: Q3 2023 | T9: Q4 2023 | U9: Q1 2024 | V9: Q2 2024 | W9: Q3 2024 | X9: Q4 2024
D10: Europe | E10: 70593 | F10: 52598 | G10: 77142 | H10: 87945 | I10: 87550 | J10: 79272 | K10: 53549 | L10: 73100 | M10: 65157 | N10: 54613 | O10: 46246 | P10: 81397 | Q10: 72671 | R10: 74272 | S10: 61826 | T10: 86025 | U10: 89670 | V10: 103964 | W10: 80785 | X10: 95266
D11: China | E11: 20780 | F11: 44961 | G11: 47537 | H11: 53339 | I11: 45242 | J11: 50010 | K11: 37358 | L11: 39066 | M11: 35698 | N11: 34535 | O11: 47511 | P11: 44578 | Q11: 36457 | R11: 42069 | S11: 45402 | T11: 46163 | U11: 37958 | V11: 40204 | W11: 34875 | X11: 43333
D12: US | E12: 19485 | F12: 23770 | G12: 30349 | H12: 36525 | I12: 27239 | J12: 36515 | K12: 31611 | L12: 26808 | M12: 22757 | N12: 27828 | O12: 21631 | P12: 29822 | Q12: 26483 | R12: 33267 | S12: 32375 | T12: 36576 | U12: 30951 | V12: 30061 | W12: 28535 | X12: 35696
D13: Other | E13: 21031 | F13: 16744 | G13: 26138 | H13: 32776 | I13: 25667 | J13: 29262 | K13: 27374 | L13: 29070 | M13: 24683 | N13: 26030 | O13: 22298 | P13: 30337 | Q13: 27327 | R13: 29145 | S13: 27864 | T13: 30794 | U13: 24108 | V13: 31157 | W13: 28654 | X13: 28172
D14: Retail sales total | E14: 131889 | F14: 138073 | G14: 181166 | H14: 210585 | I14: 185698 | J14: 195059 | K14: 149892 | L14: 168044 | M14: 148295 | N14: 143006 | O14: 137686 | P14: 186134 | Q14: 162938 | R14: 178753 | S14: 167467 | T14: 199558 | U14: 182687 | V14: =SUM(V10:V13) -> 205386 | W14: =SUM(W10:W13) -> 172849 | X14: 202467
D16: Electrified vehicles | E16: 19412 | F16: 18363 | G16: 30658 | H16: 47003 | I16: 46554 | J16: 47241 | K16: 38287 | L16: 57134 | M16: 49774 | N16: 44187 | O16: 34614 | P16: 76777 | Q16: 67403 | R16: 69015 | S16: 56810 | T16: 72752 | U16: 74995 | V16: =SUM(V17:V18) -> 98673 | W16: =SUM(W17:W18) -> 83081 | X16: 96038
D17: whereof BEV | E17: - | F17: - | G17: - | H17: 4659 | I17: 3615 | J17: 6395 | K17: 5414 | L17: 10303 | M17: 11721 | N17: 10499 | O17: 10149 | P17: 34380 | Q17: 30069 | R17: 29191 | S17: 21369 | T17: 32790 | U17: 38171 | V17: 52589 | W17: 42791 | X17: 41643
D18: whereof PHEV | E18: 19412 | F18: 18363 | G18: 30658 | H18: 42344 | I18: 42939 | J18: 40846 | K18: 32873 | L18: 46831 | M18: 38053 | N18: 33688 | O18: 24465 | P18: 42397 | Q18: 37334 | R18: 39824 | S18: 35441 | T18: 39962 | U18: 36824 | V18: 46084 | W18: 40290 | X18: 54395
D19: Electrified share | E19: 0.14718437 | F19: 0.13299487 | G19: 0.16922601 | H19: 0.22320203 | I19: 0.25069737 | J19: 0.24218826 | K19: 0.25543058 | L19: 0.33999429 | M19: 0.3356418 | N19: 0.30898704 | O19: 0.25139811 | P19: 0.41248241 | Q19: 0.41367269 | R19: 0.38609142 | S19: 0.33923101 | T19: =T16/T14 -> 0.36456569 | U19: =U16/U14 -> 0.41051087 | V19: =V16/V14 -> 0.4804271 | W19: =W16/W14 -> 0.48065653 | X19: 0.47433903
D20: whereof BEV share | H20: 0.022124083 | I20: 0.019467092 | J20: 0.032784952 | K20: 0.036119339 | L20: 0.061311323 | M20: 0.079038403 | N20: 0.0734165 | O20: 0.073711198 | P20: 0.18470564 | Q20: 0.18454259 | R20: 0.16330355 | S20: 0.12760126 | T20: =T17/T14 -> 0.16431313 | U20: =U17/U14 -> 0.20894207 | V20: =V17/V14 -> 0.25604958 | W20: =W17/W14 -> 0.2475629 | X20: 0.20567796
D22: Wholesales | E22: 142537 | F22: 135462 | G22: 166343 | H22: 218283 | I22: 177969 | J22: 178924 | K22: 128317 | L22: 169221 | M22: 156694 | N22: 135461 | O22: 145227 | P22: 194320 | Q22: 174138 | R22: 188662 | S22: 165618 | T22: 203832 | U22: 198436 | V22: 205773.99 | W22: 171261 | X22: 207114
D23: Production volume | E23: 159311 | F23: 131257 | G23: 160741 | H23: 207239 | I23: 185766 | J23: 170368 | K23: 111042 | L23: 174803 | M23: 169034 | N23: 132127 | O23: 145478 | P23: 202256 | Q23: 181144 | R23: 198395 | S23: 168971 | T23: 218234 | U23: 235481 | V23: 211940 | W23: 146614 | X23: 166348
D27: Unit | E27: Q1 2020 | F27: Q2 2020 | G27: Q3 2020 | H27: Q4 2020 | I27: Q1 2021 | J27: Q2 2021 | K27: Q3 2021 | L27: Q4 2021 | M27: Q1 2022 | N27: Q2 2022 | O27: Q3 2022 | P27: Q4 2022 | Q27: Q1 2023 | R27: Q2 2023 | S27: Q3 2023 | T27: Q4 2023 | U27: Q1 2024 | V27: Q2 2024 | W27: Q3 2024 | X27: Q4 2024
D28: EX40 (XC40 BEV) | E28: - | F28: - | G28: - | H28: 4659 | I28: 3615 | J28: 6395 | K28: 5414 | L28: 9107 | M28: 8076 | N28: 6558 | O28: 6470 | P28: 21432 | Q28: 21091 | R28: 17888 | S28: 14474 | T28: 22213 | U28: 17352 | V28: 13709 | W28: 10749 | X28: 11597
D29: EC40 (C40 BEV) | L29: 1196 | M29: 3645 | N29: 3941 | O29: 3679 | P29: 12948 | Q29: 8978 | R29: 11303 | S29: 6895 | T29: 9938 | U29: 6049 | V29: 4862 | W29: 4460 | X29: 5009
D30: EX30 | T30: 639 | U30: 14544 | V30: 33278 | W30: 27157 | X30: 23086
D31: EX90 | W31: 125 | X31: 1681
D32: EM90 | U32: 226 | V32: 740 | W32: 300 | X32: 270
D33: XC60 | E33: 36930 | F33: 41831 | G33: 52330 | H33: 60605 | I33: 52702 | J33: 60798 | K33: 49097 | L33: 53039 | M33: 44874 | N33: 48344 | O33: 48043 | P33: 54077 | Q33: 50209 | R33: 55763 | S33: 54978 | T33: 67696 | U33: 56439 | V33: 59271 | W33: 48396 | X33: 66747
D34: XC40 PHEV/ICE | E34: 34268 | F34: 34091 | G34: 53546 | H34: 58842 | I34: 53931 | J34: 54180 | K34: 33385 | L34: 35010 | M34: 34405 | N34: 29609 | O34: 28433 | P34: 34223 | Q34: 28938 | R34: 31618 | S34: 32368 | T34: 32080 | U34: 29026 | V34: 31265 | W34: 27667 | X34: 32525
D35: XC90 | E35: 18327 | F35: 19591 | G35: 23409 | H35: 31131 | I35: 24265 | J35: 29912 | K35: 26225 | L35: 27829 | M35: 21966 | N35: 26947 | O35: 22822 | P35: 25395 | Q35: 24386 | R35: 27132 | S35: 25489 | T35: 30542 | U35: 26292 | V35: 26909 | W35: 23984 | X35: 31436
D36: S90 | E36: 7155 | F36: 11300 | G36: 13083 | H36: 14489 | I36: 12044 | J36: 13609 | K36: 10640 | L36: 10275 | M36: 9489 | N36: 8336 | O36: 11462 | P36: 13623 | Q36: 10362 | R36: 12717 | S36: 13498 | T36: 12706 | U36: 10750 | V36: 11045 | W36: 9102 | X36: 9313
D37: V60/V60 | E37: 17708 | F37: 13565 | G37: 16829 | H37: 16810 | I37: 18167 | J37: 13058 | K37: 11212 | L37: 13602 | M37: 9201 | N37: 7487 | O37: 5121 | P37: 10268 | Q37: 7691 | R37: 8605 | S37: 5880 | T37: 8262 | U37: 8753 | V37: 9977 | W37: 7471 | X37: 7937
D38: S60/S60 | E38: 9154 | F38: 11304 | G38: 14449 | H38: 17344 | I38: 14060 | J38: 12299 | K38: 9765 | L38: 13120 | M38: 12173 | N38: 8161 | O38: 8686 | P38: 10484 | Q38: 8131 | R38: 9745 | S38: 10848 | T38: 11429 | U38: 10944 | V38: 11997 | W38: 11109 | X38: 9901
D39: V90/V90 | E39: 6564 | F39: 5822 | G39: 6865 | H39: 6318 | I39: 6890 | J39: 4806 | K39: 4152 | L39: 4866 | M39: 4464 | N39: 3623 | O39: 2969 | P39: 3684 | Q39: 3152 | R39: 3982 | S39: 3037 | T39: 4053 | U39: 2312 | V39: 2333 | W39: 2329 | X39: 2965
D40: V40/V40 | E40: 1783 | F40: 569 | G40: 655 | H40: 387 | I40: 24 | J40: 2 | K40: 2 | L40: 0 | M40: 2 | N40: 0 | O40: 1 | P40: 0 | Q40: 0 | R40: 0 | S40: 0 | T40: 0 | U40: 0 | V40: 0 | W40: 0 | X40: 0
D41: Total | E41: 131889 | F41: 138073 | G41: 181166 | H41: 210585 | I41: 185698 | J41: 195059 | K41: 149892 | L41: 168044 | M41: 148295 | N41: 143006 | O41: 137686 | P41: 186134 | Q41: 162938 | R41: 178753 | S41: 167467 | T41: 199558 | U41: =SUM(U28:U40) -> 182687 | V41: =SUM(V28:V40) -> 205386 | W41: =SUM(W28:W40) -> 172849 | X41: 202467

Sheet Volume Monthly
D1: Volume Monthly
E8: 2019 | R8: 2020 | AE8: 2021 | AR8: 2022 | BE8: 2023 | BR8: 2024
D9: Unit | E9: Jan | F9: Feb | G9: Mar | H9: Apr | I9: May | J9: Jun | K9: Jul | L9: Aug | M9: Sep | N9: Oct | O9: Nov | P9: Dec | R9: Jan | S9: Feb | T9: Mar | U9: Apr | V9: May | W9: Jun | X9: Jul | Y9: Aug | Z9: Sep | AA9: Oct | AB9: Nov | AC9: Dec | AE9: Jan | AF9: Feb | AG9: Mar | AH9: Apr | AI9: May | AJ9: Jun | AK9: Jul | AL9: Aug | AM9: Sep | AN9: Oct | AO9: Nov | AP9: Dec | AR9: Jan | AS9: Feb | AT9: Mar | AU9: Apr | AV9: May | AW9: June | AX9: Jul | AY9: Aug | AZ9: Sep | BA9: Oct | BB9: Nov | BC9: Dec | BE9: Jan | BF9: Feb | BG9: Mar | BH9: Apr | BI9: May | BJ9: Jun | BK9: Jul | BL9: Aug | BM9: Sep | BN9: Oct | BO9: Nov | BP9: Dec | BR9: Jan | BS9: Feb | BT9: Mar | BU9: Apr | BV9: Maj | BW9: Jun | BX9: Jul | BY9: Aug | BZ9: Sept | CA9: Oct | CB9: Nov | CC9: Dec
D10: Europe | E10: 26229 | F10: 23029 | G10: 37366 | H10: 28003 | I10: 29731 | J10: 30295 | K10: 25518 | L10: 16662 | M10: 31123 | N10: 29560 | O10: 29323 | P10: 34361 | R10: 22838 | S10: 23480 | T10: 24279 | U10: 9285 | V10: 14999 | W10: 28317 | X10: 28748 | Y10: 17502 | Z10: 30914 | AA10: 28181 | AB10: 26131 | AC10: 33633 | AE10: 24864 | AF10: 23963 | AG10: 38723 | AH10: 25816 | AI10: 24761 | AJ10: 28695 | AK10: 22408 | AL10: 13052 | AM10: 18089 | AN10: 22124 | AO10: 22415 | AP10: 28561 | AR10: 18691 | AS10: 19512 | AT10: 26954 | AU10: 19822 | AV10: 18752 | AW10: 16039 | AX10: 15893 | AY10: 10995 | AZ10: 19358 | BA10: 22030 | BB10: 25960 | BC10: 33407 | BE10: 21436 | BF10: 21278 | BG10: 29957 | BH10: 20804 | BI10: 26272 | BJ10: 27196 | BK10: 20286 | BL10: 16051 | BM10: 25489 | BN10: 24892 | BO10: 26407 | BP10: 34726 | BR10: 23141 | BS10: 26773 | BT10: 39756 | BU10: 34238 | BV10: 33252 | BW10: 36474 | BX10: 28390 | BY10: 21119 | BZ10: 31276 | CA10: 30167 | CB10: 31611 | CC10: 33488
D11: ICE | AA11: 18100 | AB11: 15278 | AC11: 19214 | AE11: 14710 | AF11: 13546 | AG11: 23452 | AH11: 14904 | AI11: 14911 | AJ11: 17129 | AK11: 12745 | AL11: 6917 | AM11: 10051 | AN11: 11755 | AO11: 10746 | AP11: 12048 | AR11: 8765 | AS11: 9618 | AT11: 12664 | AU11: 9625 | AV11: 9939 | AW11: 10613 | AX11: 9549 | AY11: 5772 | AZ11: 8157 | BA11: 7743 | BB11: 8508 | BC11: 10746 | BE11: 8616 | BF11: 7580 | BG11: 11420 | BH11: 7788 | BI11: 9791 | BJ11: 11488 | BK11: =BK10-BK14-BK13 -> 9001 | BL11: =BL10-BL14-BL13 -> 5869 | BM11: =BM10-BM14-BM13 -> 11890 | BN11: 11229 | BO11: 11754 | BP11: 15793 | BR11: 9311 | BS11: 10640 | BT11: 14900 | BU11: 11286 | BV11: 11224 | BW11: 12318 | BX11: 9908 | BY11: 5625 | BZ11: 10562 | CA11: 10191 | CB11: 11197 | CC11: 12098
D12: Electrified
D13: PHEV | AA13: 10079 | AB13: 9599 | AC13: 11228 | AE13: 9078 | AF13: 9564 | AG13: 14099 | AH13: 9698 | AI13: 8488 | AJ13: 10065 | AK13: 8531 | AL13: 5368 | AM13: 7233 | AN13: 8712 | AO13: 9891 | AP13: 13259 | AR13: 7940 | AS13: 7684 | AT13: 10894 | AU13: 7465 | AV13: 6966 | AW13: 4543 | AX13: 5350 | AY13: 3769 | AZ13: 6129 | BA13: 8115 | BB13: 9087 | BC13: 12082 | BE13: 7483 | BF13: 6983 | BG13: 9542 | BH13: 7588 | BI13: 8826 | BJ13: 10221 | BK13: 8573 | BL13: 5966 | BM13: 7378 | BN13: 6654 | BO13: 7872 | BP13: 10013 | BR13: 6359 | BS13: 7334 | BT13: 9889 | BU13: 9072 | BV13: 9755 | BW13: 10140 | BX13: 8168 | BY13: 5514 | BZ13: 8954 | CA13: 10146 | CB13: 10221 | CC13: 11803
D14: BEV | AA14: 2 | AB14: 1254 | AC14: 3191 | AE14: 1076 | AF14: 853 | AG14: 1172 | AH14: 1214 | AI14: 1362 | AJ14: 1501 | AK14: 1132 | AL14: 767 | AM14: 805 | AN14: 1657 | AO14: 1778 | AP14: 3254 | AR14: 1986 | AS14: 2210 | AT14: 3396 | AU14: 2732 | AV14: 1847 | AW14: 883 | AX14: 994 | AY14: 1454 | AZ14: 5072 | BA14: 6172 | BB14: 8365 | BC14: 10579 | BE14: 5337 | BF14: 6715 | BG14: 8995 | BH14: 5428 | BI14: 7655 | BJ14: 5487 | BK14: 2712 | BL14: 4216 | BM14: 6221 | BN14: 7009 | BO14: 6781 | BP14: 8920 | BR14: 7471 | BS14: 8799 | BT14: 14967 | BU14: 13880 | BV14: 12273 | BW14: 14016 | BX14: 10314 | BY14: 9980 | BZ14: 11760 | CA14: 9830 | CB14: 10193 | CC14: 9587
D16: China | E16: 11957 | F16: 6516 | G16: 11413 | H16: 12192 | I16: 12425 | J16: 13238 | K16: 12639 | L16: 14212 | M16: 14920 | N16: 14039 | O16: 14502 | P16: 16908 | R16: 10015 | S16: 1205 | T16: 9560 | U16: 14724 | V16: 15132 | W16: 15105 | X16: 14410 | Y16: 15835 | Z16: 17292 | AA16: 16723 | AB16: 18032 | AC16: 18584 | AE16: 19160 | AF16: 10083 | AG16: 15999 | AH16: 16435 | AI16: 16895 | AJ16: 16680 | AK16: 14550 | AL16: 13112 | AM16: 9696 | AN16: 11006 | AO16: 13418 | AP16: 14642 | AR16: 14629 | AS16: 8691 | AT16: 12378 | AU16: 8579 | AV16: 9488 | AW16: 16468 | AX16: 15487 | AY16: 17179 | AZ16: 14845 | BA16: 15048 | BB16: 12580 | BC16: 16950 | BE16: 11783 | BF16: 13066 | BG16: 11608 | BH16: 12543 | BI16: 14121 | BJ16: 15405 | BK16: 14182 | BL16: 15760 | BM16: 15460 | BN16: 15041 | BO16: 15178 | BP16: 15944 | BR16: 16042 | BS16: 7911 | BT16: 14005 | BU16: 12221 | BV16: 13934 | BW16: 14049 | BX16: 9775 | BY16: 12185 | BZ16: 12915 | CA16: 13502 | CB16: 13923 | CC16: 15908
D17: ICE | AA17: 16155 | AB17: 17162 | AC17: 17645 | AE17: 18281 | AF17: 9775 | AG17: 15245 | AH17: 15751 | AI17: 16146 | AJ17: 15921 | AK17: 13438 | AL17: 12012 | AM17: 8877 | AN17: 9776 | AO17: 11725 | AP17: 13032 | AR17: 13482 | AS17: 8009 | AT17: 11064 | AU17: 7902 | AV17: 8941 | AW17: 15793 | AX17: 14672 | AY17: 15842 | AZ17: 13788 | BA17: 14131 | BB17: 11466 | BC17: 15017 | BE17: 10525 | BF17: 11936 | BG17: 10166 | BH17: 11283 | BI17: 12940 | BJ17: 14111 | BK17: =BK16-BK20-BK19 -> 13012 | BL17: =BL16-BL20-BL19 -> 14635 | BM17: =BM16-BM20-BM19 -> 14188 | BN17: 13875 | BO17: 13835 | BP17: 14229 | BR17: 15053 | BS17: 7496 | BT17: =+BT16-BT19-BT20 -> 12966 | BU17: 11159 | BV17: 12631 | BW17: 12601 | BX17: 8645 | BY17: 10952 | BZ17: 11552 | CA17: 12066 | CB17: 12076 | CC17: 13407
D18: Electrified
D19: PHEV | AA19: 568 | AB19: 870 | AC19: 905 | AE19: 777 | AF19: 274 | AG19: 726 | AH19: 648 | AI19: 709 | AJ19: 716 | AK19: 1074 | AL19: 1048 | AM19: 730 | AN19: 1142 | AO19: 1532 | AP19: 1416 | AR19: 1039 | AS19: 618 | AT19: 1051 | AU19: 487 | AV19: 404 | AW19: 557 | AX19: 473 | AY19: 845 | AZ19: 832 | BA19: 837 | BB19: 917 | BC19: 1156 | BE19: 939 | BF19: 958 | BG19: 1007 | BH19: 918 | BI19: 918 | BJ19: 1024 | BK19: 917 | BL19: 925 | BM19: 995 | BN19: 929 | BO19: 1079 | BP19: 1466 | BR19: 828 | BS19: 278 | BT19: 670 | BU19: 604 | BV19: 671 | BW19: 1037 | BX19: 832 | BY19: 997 | BZ19: 1107 | CA19: 1195 | CB19: 1426 | CC19: 1772
D20: BEV | AA20: 0 | AB20: 0 | AC20: 34 | AE20: 102 | AF20: 34 | AG20: 28 | AH20: 36 | AI20: 40 | AJ20: 43 | AK20: 38 | AL20: 52 | AM20: 89 | AN20: 88 | AO20: 161 | AP20: 194 | AR20: 108 | AS20: 64 | AT20: 263 | AU20: 190 | AV20: 143 | AW20: 118 | AX20: 342 | AY20: 492 | AZ20: 225 | BA20: 80 | BB20: 197 | BC20: 777 | BE20: 319 | BF20: 172 | BG20: 435 | BH20: 342 | BI20: 263 | BJ20: 270 | BK20: 253 | BL20: 200 | BM20: 277 | BN20: 237 | BO20: 264 | BP20: 249 | BR20: 161 | BS20: 137 | BT20: 369 | BU20: 458 | BV20: 632 | BW20: 411 | BX20: 298 | BY20: 236 | BZ20: 256 | CA20: 241 | CB20: 421 | CC20: 729
D22: US | E22: 5854 | F22: 6635 | G22: 9569 | H22: 8367 | I22: 9761 | J22: 9934 | K22: 8795 | L22: 9194 | M22: 9323 | N22: 8807 | O22: 9635 | P22: 12360 | R22: 6157 | S22: 7841 | T22: 5487 | U22: 3866 | V22: 9519 | W22: 10385 | X22: 9697 | Y22: 10378 | Z22: 10274 | AA22: 10691 | AB22: 11590 | AC22: 14244 | AE22: 8151 | AF22: 9164 | AG22: 9924 | AH22: 11036 | AI22: 13221 | AJ22: 12258 | AK22: 11575 | AL22: 10686 | AM22: 9350 | AN22: 8701 | AO22: 7667 | AP22: 10440 | AR22: 7110 | AS22: 6219 | AT22: 9428 | AU22: 10022 | AV22: 9372 | AW22: 8434 | AX22: 6868 | AY22: 8136 | AZ22: 6627 | BA22: 9478 | BB22: 9233 | BC22: 11111 | BE22: 7693 | BF22: 8560 | BG22: 10230 | BH22: 9611 | BI22: 10723 | BJ22: 12933 | BK22: 10785 | BL22: 10644 | BM22: 10946 | BN22: 11296 | BO22: 11671 | BP22: 13609 | BR22: 7716 | BS22: 7920 | BT22: 15315 | BU22: 10604 | BV22: 10153 | BW22: 9304 | BX22: 9597 | BY22: 10420 | BZ22: 8518 | CA22: 9360 | CB22: 12259 | CC22: 14077
D23: ICE | AA23: 9694 | AB23: 10383 | AC23: 12379 | AE23: 7336 | AF23: 8126 | AG23: 8656 | AH23: 9307 | AI23: 10471 | AJ23: 9784 | AK23: 9300 | AL23: 8706 | AM23: 7650 | AN23: 6599 | AO23: 5955 | AP23: 7463 | AR23: 5202 | AS23: 4539 | AT23: 6998 | AU23: 5601 | AV23: 6024 | AW23: 6316 | AX23: 5907 | AY23: 6756 | AZ23: 5458 | BA23: 6950 | BB23: 6469 | BC23: 7909 | BE23: 5323 | BF23: 6124 | BG23: 7325 | BH23: 6665 | BI23: 7684 | BJ23: 9140 | BK23: =BK22-BK26-BK25 -> 7653 | BL23: =BL22-BL26-BL25 -> 7971 | BM23: =BM22-BM26-BM25 -> 7894 | BN23: 8255 | BO23: 8633 | BP23: 10377 | BR23: 5841 | BS23: 5349 | BT23: =+BT22-BT25-BT26 -> 11673 | BU23: 7270 | BV23: 6239 | BW23: 5989 | BX23: 5835 | BY23: 6487 | BZ23: 5102 | CA23: 5786 | CB23: 7465 | CC23: 9305
D24: Electrified
D25: PHEV | AA25: 995 | AB25: 1154 | AC25: 1765 | AE25: 672 | AF25: 913 | AG25: 1216 | AH25: 1396 | AI25: 1805 | AJ25: 1746 | AK25: 1374 | AL25: 1272 | AM25: 1217 | AN25: 1295 | AO25: 1300 | AP25: 2222 | AR25: 1480 | AS25: 1124 | AT25: 1756 | AU25: 3628 | AV25: 2541 | AW25: 1565 | AX25: 867 | AY25: 1174 | AZ25: 1015 | BA25: 1693 | BB25: 1688 | BC25: 2070 | BE25: 1599 | BF25: 1463 | BG25: 1867 | BH25: 1590 | BI25: 1697 | BJ25: 1670 | BK25: 1877 | BL25: 1814 | BM25: 1926 | BN25: 1801 | BO25: 2198 | BP25: 2546 | BR25: 1615 | BS25: 2212 | BT25: 3291 | BU25: 3006 | BV25: 3617 | BW25: 2929 | BX25: 3242 | BY25: 3345 | BZ25: 2750 | CA25: 3003 | CB25: 4301 | CC25: 3983
D26: BEV | AA26: 2 | AB26: 53 | AC26: 100 | AE26: 143 | AF26: 125 | AG26: 52 | AH26: 333 | AI26: 945 | AJ26: 728 | AK26: 901 | AL26: 708 | AM26: 483 | AN26: 807 | AO26: 412 | AP26: 755 | AR26: 428 | AS26: 556 | AT26: 674 | AU26: 793 | AV26: 807 | AW26: 553 | AX26: 94 | AY26: 206 | AZ26: 154 | BA26: 835 | BB26: 1076 | BC26: 1132 | BE26: 771 | BF26: 973 | BG26: 1038 | BH26: 1356 | BI26: 1342 | BJ26: 2123 | BK26: 1255 | BL26: 859 | BM26: 1126 | BN26: 1240 | BO26: 840 | BP26: 686 | BR26: 260 | BS26: 359 | BT26: 351 | BU26: 328 | BV26: 297 | BW26: 386 | BX26: 520 | BY26: 588 | BZ26: 666 | CA26: 571 | CB26: 493 | CC26: 789
D28: Other | E28: 6639 | F28: 7004 | G28: 9109 | H28: 7973 | I28: 8279 | J28: 9308 | K28: 7594 | L28: 7728 | M28: 9170 | N28: 8553 | O28: 9090 | P28: 10610 | R28: 6742 | S28: 7216 | T28: 7069 | U28: 3885 | V28: 5180 | W28: 7676 | X28: 9436 | Y28: 7524 | Z28: 9156 | AA28: 9695 | AB28: 10826 | AC28: 12255 | AE28: 7413 | AF28: 7585 | AG28: 10669 | AH28: 9437 | AI28: 9234 | AJ28: 10591 | AK28: 8350 | AL28: 8936 | AM28: 10088 | AN28: 8984 | AO28: 9293 | AP28: 10793 | AR28: 7131 | AS28: 7645 | AT28: 9907 | AU28: 8727 | AV28: 8340 | AW28: 8963 | AX28: 6416 | AY28: 7356 | AZ28: 8526 | BA28: 7761 | BB28: 11381 | BC28: 11195 | BE28: 7608 | BF28: 8382 | BG28: 11337 | BH28: 9018 | BI28: 9282 | BJ28: 10845 | BK28: 8912 | BL28: 9181 | BM28: 9771 | BN28: 8632 | BO28: 10426 | BP28: 11736 | BR28: 6503 | BS28: 7711 | BT28: 9894 | BU28: 8775 | BV28: 10695 | BW28: 11687 | BX28: 9685 | BY28: 9220 | BZ28: 9749 | CA28: 8657 | CB28: 9184 | CC28: 10331
D29: ICE | AA29: 8601 | AB29: 9048 | AC29: 9923 | AE29: 5747 | AF29: 5812 | AG29: 8458 | AH29: 7511 | AI29: 7391 | AJ29: 8592 | AK29: 6875 | AL29: 7089 | AM29: 7945 | AN29: 6699 | AO29: 7064 | AP29: 8048 | AR29: 5041 | AS29: 6036 | AT29: 7103 | AU29: 5925 | AV29: 5603 | AW29: 6537 | AX29: 4940 | AY29: 5714 | AZ29: 6517 | BA29: 5496 | BB29: 7757 | BC29: 7165 | BE29: 4314 | BF29: 4968 | BG29: 7238 | BH29: 5612 | BI29: 6016 | BJ29: 7220 | BK29: =BK28-BK32-BK31 -> 5797 | BL29: =BL28-BL32-BL31 -> 6156 | BM29: =BM28-BM32-BM31 -> 6591 | BN29: 5159 | BO29: 6512 | BP29: 7155 | BR29: 4026 | BS29: 4564 | BT29: =+BT28-BT31-BT32 -> 5873 | BU29: 4600 | BV29: 5172 | BW29: 6224 | BX29: 5180 | BY29: 4852 | BZ29: 5068 | CA29: 3748 | CB29: 4131 | CC29: 4959
D30: Electrified
D31: PHEV | AA31: 1094 | AB31: 1778 | AC31: 2309 | AE31: 1648 | AF31: 1772 | AG31: 2200 | AH31: 1823 | AI31: 1791 | AJ31: 1961 | AK31: 1411 | AL31: 1730 | AM31: 1885 | AN31: 1996 | AO31: 1887 | AP31: 2179 | AR31: 1485 | AS31: 1101 | AT31: 1881 | AU31: 1808 | AV31: 1882 | AW31: 1842 | AX31: 1323 | AY31: 1300 | AZ31: 1388 | BA31: 1204 | BB31: 1618 | BC31: 1930 | BE31: 1847 | BF31: 1700 | BG31: 1946 | BH31: 1702 | BI31: 1700 | BJ31: 1970 | BK31: 1831 | BL31: 1640 | BM31: 1599 | BN31: 1470 | BO31: 1768 | BP31: 2166 | BR31: 1143 | BS31: 1518 | BT31: 1687 | BU31: 1751 | BV31: 1661 | BW31: 1841 | BX31: 1507 | BY31: 1754 | BZ31: 2120 | CA31: 2111 | CB31: 2087 | CC31: 2347
D32: BEV | AA32: 0 | AB32: 0 | AC32: 23 | AE32: 18 | AF32: 1 | AG32: 11 | AH32: 103 | AI32: 52 | AJ32: 38 | AK32: 64 | AL32: 117 | AM32: 258 | AN32: 289 | AO32: 342 | AP32: 566 | AR32: 605 | AS32: 508 | AT32: 923 | AU32: 994 | AV32: 855 | AW32: 584 | AX32: 153 | AY32: 342 | AZ32: 621 | BA32: 1061 | BB32: 2006 | BC32: 2100 | BE32: 1447 | BF32: 1714 | BG32: 2153 | BH32: 1704 | BI32: 1566 | BJ32: 1655 | BK32: 1284 | BL32: 1385 | BM32: 1581 | BN32: 2003 | BO32: 2146 | BP32: 2415 | BR32: 1334 | BS32: 1629 | BT32: 2334 | BU32: 2424 | BV32: 3862 | BW32: 3622 | BX32: 2998 | BY32: 2614 | BZ32: 2561 | CA32: 2798 | CB32: 2966 | CC32: 3025
D34: Total | E34: 50679 | F34: 43184 | G34: 67457 | H34: 56535 | I34: 60196 | J34: 62775 | K34: 54546 | L34: 47796 | M34: 64536 | N34: 60959 | O34: 62550 | P34: 74239 | R34: 45752 | S34: 39742 | T34: 46395 | U34: 31760 | V34: 44830 | W34: 61483 | X34: 62291 | Y34: 51239 | Z34: 67636 | AA34: 65290 | AB34: 66579 | AC34: 78716 | AE34: 59588 | AF34: 50795 | AG34: 75315 | AH34: 62724 | AI34: 64111 | AJ34: 68224 | AK34: 56883 | AL34: 45786 | AM34: 47223 | AN34: 50815 | AO34: 52793 | AP34: 64436 | AR34: 47561 | AS34: 42067 | AT34: 58667 | AU34: 47150 | AV34: 45952 | AW34: 49904 | AX34: 44664 | AY34: 43666 | AZ34: 49356 | BA34: 54317 | BB34: 59154 | BC34: 72663 | BE34: 48520 | BF34: 51286 | BG34: 63132 | BH34: 51976 | BI34: 60398 | BJ34: 66379 | BK34: 54165 | BL34: 51636 | BM34: 61666 | BN34: 59861 | BO34: 63682 | BP34: 76015 | BR34: 53402 | BS34: 50315 | BT34: 78970 | BU34: =BU28+BU22+BU16+BU10 -> 65838 | BV34: =BV28+BV22+BV16+BV10 -> 68034 | BW34: =BW28+BW22+BW16+BW10 -> 71514 | BX34: 57447 | BY34: 52944 | BZ34: 62458 | CA34: 61686 | CB34: 66977 | CC34: 73804
D35: ICE | AA35: 52550 | AB35: 51871 | AC35: 59161 | AE35: 46074 | AF35: 37259 | AG35: 55811 | AH35: 47473 | AI35: 48919 | AJ35: 51426 | AK35: 42358 | AL35: 34724 | AM35: 34523 | AN35: 34829 | AO35: 35490 | AP35: 40591 | AR35: 32490 | AS35: 28202 | AT35: 37829 | AU35: 29053 | AV35: 30507 | AW35: 39259 | AX35: 35068 | AY35: 34084 | AZ35: 33920 | BA35: 34320 | BB35: 34200 | BC35: 40837 | BE35: 28778 | BF35: 30608 | BG35: 36149 | BH35: 31348 | BI35: 36431 | BJ35: 41959 | BK35: =SUM(BK29,BK23,BK17,BK11) -> 35463 | BL35: =SUM(BL29,BL23,BL17,BL11) -> 34631 | BM35: =SUM(BM29,BM23,BM17,BM11) -> 40563 | BN35: =SUM(BN29,BN23,BN17,BN11) -> 38518 | BO35: =SUM(BO29,BO23,BO17,BO11) -> 40734 | BP35: =SUM(BP29,BP23,BP17,BP11) -> 47554 | BR35: 34231 | BS35: 28049 | BT35: 45412 | BU35: =BU29+BU23+BU17+BU11 -> 34315 | BV35: =BV29+BV23+BV17+BV11 -> 35266 | BW35: =BW29+BW23+BW17+BW11 -> 37132 | BX35: =BX29+BX23+BX17+BX11 -> 29568 | BY35: =BY29+BY23+BY17+BY11 -> 27916 | BZ35: =BZ29+BZ23+BZ17+BZ11 -> 32284 | CA35: 31791 | CB35: 34869 | CC35: 39769
D36: Electrified
D37: PHEV | AA37: 12736 | AB37: 13401 | AC37: 16207 | AE37: 12175 | AF37: 12523 | AG37: 18241 | AH37: 13565 | AI37: 12793 | AJ37: 14488 | AK37: 12390 | AL37: 9418 | AM37: 11065 | AN37: 13145 | AO37: 14610 | AP37: 19076 | AR37: 11944 | AS37: 10527 | AT37: 15582 | AU37: 13388 | AV37: 11793 | AW37: 8507 | AX37: 8013 | AY37: 7088 | AZ37: 9364 | BA37: 11849 | BB37: 13310 | BC37: 17238 | BE37: 11868 | BF37: 11104 | BG37: 14362 | BH37: 11798 | BI37: 13141 | BJ37: 14885 | BK37: =SUM(BK31,BK25,BK19,BK13) -> 13198 | BL37: =SUM(BL31,BL25,BL19,BL13) -> 10345 | BM37: =SUM(BM31,BM25,BM19,BM13) -> 11898 | BN37: =SUM(BN31,BN19,BN13) -> 9053 | BO37: =SUM(BO31,BO25,BO19,BO13) -> 12917 | BP37: =SUM(BP31,BP25,BP13) -> 14725 | BR37: 9945 | BS37: 11342 | BT37: 15537 | BU37: =BU31+BU25+BU19+BU13 -> 14433 | BV37: =BV31+BV25+BV19+BV13 -> 15704 | BW37: =BW31+BW25+BW19+BW13 -> 15947 | BX37: =BX31+BX25+BX19+BX13 -> 13749 | BY37: =BY31+BY25+BY19+BY13 -> 11610 | BZ37: =BZ31+BZ25+BZ19+BZ13 -> 14931 | CA37: 16455 | CB37: 18035 | CC37: 19905
D38: BEV | AA38: 4 | AB38: 1307 | AC38: 3348 | AE38: 1339 | AF38: 1013 | AG38: 1263 | AH38: 1686 | AI38: 2399 | AJ38: 2310 | AK38: 2135 | AL38: 1644 | AM38: 1635 | AN38: 2841 | AO38: 2693 | AP38: 4769 | AR38: 3127 | AS38: 3338 | AT38: 5256 | AU38: 4709 | AV38: 3652 | AW38: 2138 | AX38: 1583 | AY38: 2494 | AZ38: 6072 | BA38: 8148 | BB38: 11644 | BC38: 14588 | BE38: 7874 | BF38: 9574 | BG38: 12621 | BH38: 8830 | BI38: 10826 | BJ38: 9535 | BK38: =SUM(BK32,BK26,BK20,BK14) -> 5504 | BL38: =SUM(BL32,BL26,BL20,BL14) -> 6660 | BM38: =SUM(BM32,BM26,BM20,BM14) -> 9205 | BN38: =SUM(BN32,BN20,BN26,BN14) -> 10489 | BO38: =SUM(BO32,BO26,BO20,BO14) -> 10031 | BP38: =SUM(BP32,BP20,BP26,BP14) -> 12270 | BR38: 9226 | BS38: 10924 | BT38: 18021 | BU38: =BU32+BU26+BU20+BU14 -> 17090 | BV38: =BV32+BV26+BV20+BV14 -> 17064 | BW38: =BW32+BW26+BW20+BW14 -> 18435 | BX38: =BX32+BX26+BX20+BX14 -> 14130 | BY38: =BY32+BY26+BY20+BY14 -> 13418 | BZ38: =BZ32+BZ26+BZ20+BZ14 -> 15243 | CA38: 13440 | CB38: 14073 | CC38: 14130

Sheet Revenue and EBIT walk
D1: EBIT and Revenue walk
D9: Changes to Operating income (EBIT), MSEK | E9: Full year 2018 | F9: Full year 2019 | G9: Full year 2020 | H9: Full year 2021 | I9: Full year 2022 | J9: Full year 2023 | K9: Full year 2024 | M9: Q1 2018 | N9: Q2 2018 | O9: Q3 2018 | P9: Q4 2018 | Q9: Q1 2019 | R9: Q2 2019 | S9: Q3 2019 | T9: Q4 20191) | U9: Q1 2020 | V9: Q2 2020 | W9: Q3 2020 | X9: Q4 2020 | Y9: Q1 2021 | Z9: Q2 2021 | AA9: Q3 2021 | AB9: Q4 2021 | AC9: Q1 2022 | AD9: Q2 2022 | AE9: Q3 2022 | AF9: Q4 2022 | AG9: Q1 2023 | AH9: Q2 2023 | AI9: Q3 2023 | AJ9: Q4 2023 | AK9: Q1 2024 | AL9: Q2 2024 | AM9: Q3 2024 | AN9: Q4 2024
D10: Opening balance | E10: 14061 | F10: 14185 | G10: 14303 | H10: 8036 | I10: 20275 | J10: 22332 | K10: 19939 | M10: 3491 | N10: 3285 | O10: 3669 | P10: 3616 | Q10: 3616 | R10: 4226 | S10: 1838 | T10: 4505 | U10: 2919 | V10: 2600 | W10: 3492 | X10: 5292 | Y10: 639 | Z10: -1628 | AA10: 4568 | AB10: 4937 | AC10: 8423 | AD10: 4815 | AE10: 3329 | AF10: 3708 | AG10: 6038 | AH10: 10801 | AI10: 2050 | AJ10: 3443 | AK10: 5100 | AL10: 4993 | AM10: 4458 | AN10: 5388
D11: Volume | E11: 5599 | F11: 5588 | G11: -2968 | H11: 559 | I11: -22 | J11: 12253 | K11: 605 | M11: 1392 | N11: 1957 | O11: 1006 | P11: 1244 | Q11: 955 | R11: 1164 | S11: 1679 | T11: 1790 | U11: -2129 | V11: -2723 | W11: 270 | X11: 1614 | Y11: 2880 | Z11: 2895 | AA11: -2287 | AB11: -2929 | AC11: -1325 | AD11: -2845 | AE11: 1945 | AF11: 2203 | AG11: 2936 | AH11: 5846 | AI11: 2395 | AJ11: 1076 | AK11: 1148 | AL11: 468 | AM11: -39 | AN11: -972
D12: Sales mix and pricing | E12: 690 | F12: -4060 | G12: -1750 | H12: 9536 | I12: 9233 | J12: -511 | K12: -5017 | M12: 370 | N12: -40 | O12: 165 | P12: 195 | Q12: -555 | R12: -1805 | S12: -785 | T12: -915 | U12: -735 | V12: -325 | W12: -35 | X12: -655 | Y12: 1002 | Z12: 2720 | AA12: 2598 | AB12: 3216 | AC12: 2494 | AD12: 3551 | AE12: 1123 | AF12: 2065 | AG12: 902 | AH12: -1843 | AI12: -437 | AJ12: 867 | AK12: -2016 | AL12: 267 | AM12: -2388 | AN12: -880
D13: Government grants | E13: 628 | F13: -1506 | G13: -383 | H13: -127 | I13: 54 | J13: -6 | K13: -236 | M13: 496 | N13: 619 | O13: 45 | P13: -533 | Q13: -605 | R13: -785 | S13: -267 | T13: 150 | U13: -56 | V13: 150 | W13: -132 | X13: -345 | Y13: -5 | Z13: -123 | AA13: -308 | AB13: -78 | AC13: 52 | AD13: -78 | AE13: 71 | AF13: 9 | AG13: -72 | AH13: 34 | AI13: 65 | AJ13: 29 | AK13: -17 | AL13: -46 | AM13: -163 | AN13: -10
D14: Sale of licences | E14: - | F14: -65 | G14: 450 | H14: -219 | I14: -103 | J14: -83 | K14: -107 | M14: - | N14: - | O14: - | P14: - | Q14: 250 | R14: 620 | S14: 60 | T14: -995 | U14: 390 | V14: -310 | W14: 220 | X14: 150 | Y14: -225 | Z14: 130 | AA14: 35 | AB14: -159 | AC14: 98 | AD14: -146 | AE14: -202 | AF14: 147 | AG14: -392 | AH14: 215 | AI14: 72 | AJ14: -40 | AK14: 226 | AL14: -212 | AM14: -103 | AN14: -18
D15: Foreign exchange rates | E15: -485 | F15: -125 | G15: -4970 | H15: 400 | I15: 777 | J15: 1824 | K15: 121 | M15: -635 | N15: 740 | O15: 290 | P15: -880 | Q15: 120 | R15: -595 | S15: 495 | T15: -145 | U15: -575 | V15: -745 | W15: -1580 | X15: -2070 | Y15: -950 | Z15: -420 | AA15: 681 | AB15: 1089 | AC15: -492 | AD15: 1783 | AE15: 64 | AF15: -578 | AG15: 1209 | AH15: 869 | AI15: 332 | AJ15: -586 | AK15: 378 | AL15: -940 | AM15: -1259 | AN15: 1942
D16: Share of income in joint ventures and associates2) | E16: -133 | F16: -235 | G16: -856 | H16: -3141 | I16: 5394 | J16: -4172 | K16: 2608 | M16: -33 | N16: 129 | O16: 10 | P16: -239 | Q16: -57 | R16: -156 | S16: -396 | T16: 374 | U16: -413 | V16: -322 | W16: 99 | X16: -220 | Y16: 119 | Z16: -549 | AA16: -737 | AB16: -1974 | AC16: -2734 | AD16: 7088 | AE16: -476 | AF16: 1516 | AG16: -1376 | AH16: -1724 | AI16: -227 | AJ16: - | AK16: -874 | AL16: 1187 | AM16: 1770 | AN16: 525
D17: Items affecting comparability - Volvo Cars operations | E17: - | F17: - | G17: 1013 | H17: -930 | I17: 0 | J17: -624 | K17: 624 | M17: - | N17: - | O17: - | P17: - | Q17: - | R17: - | S17: - | T17: - | U17: - | V17: 1074 | W17: - | X17: -61 | Y17: 55 | Z17: -1063 | AA17: - | AB17: 78 | AC17: -9 | AD17: -10 | AE17: 4 | AF17: 15 | AG17: - | AH17: -880 | AI17: 256 | AJ17: - | AK17: - | AL17: 880 | AM17: -256 | AN17: -
D18: Items affecting comparability - Joint ventures and associates | E18: - | F18: - | G18: 672 | H18: 2542 | I18: 0 | J18: -5899 | K18: -1702 | M18: - | N18: - | O18: - | P18: - | Q18: - | R18: - | S18: - | T18: - | U18: - | V18: - | W18: 672 | X18: - | Y18: 3214 | Z18: - | AA18: -672 | AB18: - | AC18: - | AD18: - | AE18: - | AF18: - | AG18: - | AH18: -5899 | AI18: - | AJ18: -845 | AK18: - | AL18: - | AM18: - | AN18: -1702
D19: Other3) | E19: -6175 | F19: 521 | G19: 2525 | H19: 3619 | I19: -13276 | J19: -5175 | K19: 5483 | M19: -1465 | N19: -2464 | O19: -3347 | P19: 1102 | Q19: -805 | R19: -69 | S19: 868 | T19: 528 | U19: 1238 | V19: -1027 | W19: 1175 | X19: 1139 | Y19: 1694 | Z19: 2853 | AA19: -549 | AB19: -472 | AC19: -469 | AD19: -3357 | AE19: -3808 | AF19: -5642 | AG19: -4145 | AH19: -2426 | AI19: -48 | AJ19: 1444 | AK19: 761 | AL19: 1372 | AM19: 3771 | AN19: -420
D20: Closing Balance | E20: 14185 | F20: 14303 | G20: 8036 | H20: 20275 | I20: 22332 | J20: 19939 | K20: 22318 | M20: 3616 | N20: 4226 | O20: 1838 | P20: 4505 | Q20: 2919 | R20: 2600 | S20: 3492 | T20: 5292 | U20: 639 | V20: -1628 | W20: 4181 | X20: 4844 | Y20: 8423 | Z20: 4815 | AA20: 3329 | AB20: 3708 | AC20: 6038 | AD20: 10801 | AE20: 2050 | AF20: 3443 | AG20: =SUM(AG10:AG19) -> 5100 | AH20: 4993 | AI20: 4458 | AJ20: 5388 | AK20: 4706 | AL20: 7969 | AM20: 5791 | AN20: 3853
D23: Changes to Revenue, MSEK | E23: Full year 2018 | F23: Full year 2019 | G23: Full year 2020 | H23: Full year 2021 | I23: Full year 2022 | J23: Full year 2023 | K23: Full year 2024 | M23: Q1 2018 | N23: Q2 2018 | O23: Q3 2018 | P23: Q4 2018 | Q23: Q1 2019 | R23: Q2 2019 | S23: Q3 2019 | T23: Q4 20191) | U23: Q1 2020 | V23: Q2 2020 | W23: Q3 2020 | X23: Q4 2020 | Y23: Q1 2021 | Z23: Q2 2021 | AA23: Q3 2021 | AB23: Q4 20215) | AC23: Q1 2022 | AD23: Q2 2022 | AE23: Q3 2022 | AF23: Q4 2022 | AG23: Q1 2023 | AH23: Q2 2023 | AI23: Q3 2023 | AJ23: Q4 2023 | AK23: Q1 2024 | AL23: Q2 2024 | AM23: Q3 2024 | AN23: Q4 2024
D24: Opening balance | E24: 208646 | F24: 252653 | G24: 274117 | H24: 262833 | I24: 282045 | J24: 330145 | K24: 399343 | M24: 47373 | N24: 52043 | O24: 48271 | P24: 60959 | Q24: 56813 | R24: 66039 | S24: 56776 | T24: 73025 | U24: 62910 | V24: 67185 | W24: 64827 | X24: 79195 | Y24: 56517 | Z24: 55242 | AA24: 65763 | AB24: 85311 | AC24: 68593 | AD24: 72538 | AE24: 60838 | AF24: 80076 | AG24: 74269 | AH24: 71300 | AI24: 79329 | AJ24: 105247 | AK24: 95705 | AL24: 102152 | AM24: 92045 | AN24: 109441
D25: Volume | E25: 20979 | F25: 17104 | G25: -10371 | H25: 2716 | I25: -3125 | J25: 41796 | K25: 25184 | M25: 5022 | N25: 7081 | O25: 4802 | P25: 4074 | Q25: 4058 | R25: 2071 | S25: 5268 | T25: 5707 | U25: -7776 | V25: -11385 | W25: 2221 | X25: 6569 | Y25: 12199 | Z25: 14208 | AA25: -8929 | AB25: -14762 | AC25: -5829 | AD25: -12168 | AE25: 4656 | AF25: 10216 | AG25: 8983 | AH25: 20007 | AI25: 8914 | AJ25: 3892 | AK25: 4492 | AL25: 9031 | AM25: 4955 | AN25: -520
D26: Deferred revenue | J26: - | K26: - | AF26: - | AG26: - | AH26: - | AI26: - | AJ26: - | AK26: - | AL26: -4949 | AM26: -1551 | AN26: -
D27: Used cars and deferred revenue | J27: - | K27: -7182 | AG27: - | AH27: - | AI27: - | AJ27: - | AK27: - | AL27: - | AM27: - | AN27: 1369
D28: Sales mix and pricing | E28: 10500 | F28: -5800 | G28: 4135 | H28: 20405 | I28: 15160 | J28: 4719 | K28: -6261 | M28: 4150 | N28: 3550 | O28: 1540 | P28: 1260 | Q28: -735 | R28: -3385 | S28: -215 | T28: -1465 | U28: 320 | V28: 2070 | W28: 410 | X28: 1335 | Y28: 3970 | Z28: 5024 | AA28: 4112 | AB28: 7299 | AC28: 4068 | AD28: 5530 | AE28: 2776 | AF28: 2786 | AG28: 4179 | AH28: -491 | AI28: -417 | AJ28: 1448 | AK28: -1906 | AL28: -2116 | AM28: -1564 | AN28: -675
D29: Sale of licences | E29: - | F29: -922 | G29: 125 | H29: -488 | I29: -569 | J29: -80 | K29: -150 | M29: - | N29: - | O29: - | P29: - | Q29: 275 | R29: 595 | S29: 430 | T29: -2222 | U29: 365 | V29: -280 | W29: -15 | X29: 55 | Y29: -294 | Z29: 67 | AA29: -23 | AB29: -238 | AC29: 49 | AD29: -267 | AE29: -182 | AF29: -169 | AG29: -404 | AH29: 274 | AI29: 22 | AJ29: 28 | AK29: 256 | AL29: -198 | AM29: -88 | AN29: -120
D30: Foreign exchange rates | E30: 6830 | F30: 8530 | G30: -6660 | H30: -9732 | I30: 21802 | J30: 14276 | K30: -6122 | M30: -480 | N30: 1535 | O30: 3130 | P30: 2645 | Q30: 2355 | R30: 1635 | S30: 1850 | T30: 2690 | U30: 1260 | V30: -190 | W30: -3260 | X30: -4470 | Y30: -4740 | Z30: -4250 | AA30: -467 | AB30: -275 | AC30: 3983 | AD30: 3977 | AE30: 5952 | AF30: 7890 | AG30: 5257 | AH30: 5096 | AI30: 2255 | AJ30: 1668 | AK30: -2098 | AL30: -176 | AM30: -1804 | AN30: -2044
D31: Contract manfacturing4) | E31: - | F31: - | G31: - | H31: - | I31: 17696 | J31: 1801 | K31: -8832 | M31: - | N31: - | O31: - | P31: - | Q31: - | R31: - | S31: - | T31: - | U31: - | V31: - | W31: - | X31: - | Y31: - | Z31: - | AA31: - | AB31: - | AC31: 3529 | AD31: 2084 | AE31: 6437 | AF31: 5646 | AG31: 2674 | AH31: 3739 | AI31: -244 | AJ31: -4368 | AK31: -4339 | AL31: -3162 | AM31: -1252 | AN31: -129
D32: Other5) | E32: 5698 | F32: 2552 | G32: 1487 | H32: 6311 | I32: -2864 | J32: 6686 | K32: 4254 | M32: 748 | N32: 1830 | O32: -967 | P32: 4087 | Q32: 144 | R32: 230 | S32: 718 | T32: 1460 | U32: -562 | V32: -2158 | W32: 1580 | X32: 2627 | Y32: 941 | Z32: 2247 | AA32: 382 | AB32: 2741 | AC32: -124 | AD32: -394 | AE32: -1147 | AF32: -1199 | AG32: 747 | AH32: 2227 | AI32: =2188-45 -> 2143 | AJ32: =1524+2 -> 1526 | AK32: 1768 | AL32: 872 | AM32: 2042 | AN32: 4797
D33: Closing Balance | E33: 252653 | F33: 274117 | G33: 262833 | H33: 282045 | I33: 330145 | J33: 399343 | K33: 400234 | M33: 56813 | N33: 66039 | O33: 56776 | P33: 73025 | Q33: 62910 | R33: 67185 | S33: 64827 | T33: 79195 | U33: 56517 | V33: 55242 | W33: 65763 | X33: 85311 | Y33: 68593 | Z33: 72538 | AA33: 60838 | AB33: 80076 | AC33: 74269 | AD33: 71300 | AE33: 79329 | AF33: 105247 | AG33: 95705 | AH33: 102152 | AI33: =92047-2 -> 92045 | AJ33: =109439+2 -> 109441 | AK33: 93878 | AL33: 101454 | AM33: 92783 | AN33: 112119
D36: 1) Starting from Q4 2019, the Rental business effect is classified as Volume effect.
D37: 2) Excluding Items affecting comparability - Joint ventures and associates, until Q1 2022. In Q2 and Q3 2022, items affecting comparability - Joint ventures and associates, is included.
D38: 3) Mainly including used cars, parts and accessories, contract manufacturing, raw material increase and cost efficiencies.
D39: 4) In Q4 2021, Contract manufacturing was included in Other.
D40: 5) Including used cars, parts and accessories.

Sheet Income Statement
D1: Income Statement
E8: Yearly | T8: Quarterly
D9: MSEK | E9: Full Year 20121) | F9: Full Year 20131) | G9: Full Year 20142) | H9: Full Year 20153)4)5)6) | I9: Full Year 20163)4)5)6) | J9: Full Year 20174)5)6) | K9: Full year 20186) | L9: Full year 2019 | M9: Full year 20209) | N9: Full year 20217)8) | O9: Full year 2022 | P9: Full year 2023 | Q9: Full year 2024 | T9: Q1 2020 | U9: Q2 2020 | V9: Q3 20209) | W9: Q4 20209) | X9: Q1 20218) | Y9: Q2 20218) | Z9: Q3 20218) | AA9: Q4 20217)8) | AB9: Q1 2022 | AC9: Q2 2022 | AD9: Q3 2022 | AE9: Q4 2022 | AF9: Q1 2023 | AG9: Q2 2023 | AH9: Q3 2023 | AI9: Q4 2023 | AJ9: Q1 2024 | AK9: Q2 2024 | AL9: Q3 2024 | AM9: Q4 2024
D10: Net revenue | E10: 124547 | F10: 122245 | G10: 137590 | H10: 160515 | I10: 178586 | J10: 208646 | K10: 252653 | L10: 274117 | M10: 262833 | N10: 282045 | O10: 330145 | P10: 399343 | Q10: 400234 | T10: 56517 | U10: 55242 | V10: 65763 | W10: 85311 | X10: 68593 | Y10: 72538 | Z10: 60838 | AA10: 80076 | AB10: 74269 | AC10: 71300 | AD10: 79329 | AE10: 105247 | AF10: 95705 | AG10: 102152 | AH10: 92045 | AI10: 109441 | AJ10: 93878 | AK10: 101454 | AL10: 92783 | AM10: 112119
D11: Cost of sales | E11: -104600 | F11: -101934 | G11: -114019 | H11: -125534 | I11: -139904 | J11: -161988 | K11: -203322 | L11: -222047 | M11: -216880 | N11: -221254 | O11: -269813 | P11: -321916 | Q11: -320821 | T11: -46762 | U11: -47718 | V11: =-52913 -> -52913 | W11: =-69420-67 -> -69487 | X11: =-54517+77.96 -> -54439.04 | Y11: =-56503+119.883 -> -56383.117 | Z11: =-47101+82.248 -> -47018.752 | AA11: =-63511+98.195 -> -63412.805 | AB11: -58555 | AC11: -57204 | AD11: -65612 | AE11: -88442 | AF11: -78606 | AG11: -82733 | AH11: -73968 | AI11: -86609 | AJ11: -75806 | AK11: -78272 | AL11: -73747 | AM11: -92997
D12: Gross income | E12: 19947 | F12: 20311 | G12: 23571 | H12: 34981 | I12: 38682 | J12: 46658 | K12: 49331 | L12: 52070 | M12: 45953 | N12: 60791 | O12: 60332 | P12: 77427 | Q12: 79413 | T12: 9755 | U12: 7524 | V12: =12850 -> 12850 | W12: =SUM(W10:W11) -> 15824 | X12: 14154 | Y12: 16155 | Z12: 13819 | AA12: 16663 | AB12: 15714 | AC12: 14096 | AD12: 13717 | AE12: 16805 | AF12: 17099 | AG12: 19419 | AH12: 18077 | AI12: 22832 | AJ12: 18072 | AK12: 23182 | AL12: 19036 | AM12: 19122
D14: Research and development expenses | E14: -6289 | F14: -5864 | G14: -7193 | H14: -9480 | I14: -10174 | J14: -10187 | K14: -10903 | L14: -11446 | M14: -11362 | N14: -12714 | O14: -11514 | P14: -12884 | Q14: -16983 | T14: -2706 | U14: -3272 | V14: -3299 | W14: -2085 | X14: =-3503+84.898 -> -3418.102 | Y14: =-3645+130.465 -> -3514.535 | Z14: =-2689+89.545 -> -2599.455 | AA14: =-3289+106.907 -> -3182.093 | AB14: -3230 | AC14: -2918 | AD14: -2817 | AE14: -2549 | AF14: -2878 | AG14: -3383 | AH14: -2909 | AI14: -3714 | AJ14: -3827 | AK14: -4725 | AL14: -3403 | AM14: -5028
D15: Selling expenses | E15: -8642 | F15: -7919 | G15: -8708 | H15: -10951 | I15: -11992 | J15: -15266 | K15: -17371 | L15: -17287 | M15: -16097 | N15: -18796 | O15: -21000 | P15: -26056 | Q15: -25409 | T15: -3790 | U15: -3267 | V15: =-3572-387 -> -3959 | W15: -5081 | X15: =-4003+69.41+18.297 -> -3915.293 | Y15: =-4967+100.576+28.137 -> -4838.287 | Z15: =-4802+71.129+19.247 -> -4711.624 | AA15: =-5439+84.92+22.979 -> -5331.101 | AB15: -4586 | AC15: -4565 | AD15: -5114 | AE15: -6735 | AF15: -5789 | AG15: -6612 | AH15: -6576 | AI15: -7079 | AJ15: -5772 | AK15: -6789 | AL15: -6623 | AM15: -6225
D16: Administrative expenses | E16: -5240 | F16: -5129 | G16: -5943 | H16: -7234 | I16: -6471 | J16: -8182 | K16: -8001 | L16: -9489 | M16: -8565 | N16: -9698 | O16: -11485 | P16: -12539 | Q16: -12038 | T16: -2097 | U16: -2134 | V16: =-1840 -> -1840 | W16: -2494 | X16: =-1922-250.564 -> -2172.564 | Y16: =-1690-379.011 -> -2069.011 | Z16: =-2516-262.168 -> -2778.168 | AA16: =-2365-313.002 -> -2678.002 | AB16: -2600 | AC16: -2930 | AD16: -2905 | AE16: -3050 | AF16: -2765 | AG16: -3469 | AH16: -2945 | AI16: -3360 | AJ16: -2784 | AK16: -2942 | AL16: -3001 | AM16: -3311
D17: Other operating income and expenses | E17: 218 | F17: 341 | G17: 210 | H17: -926 | I17: 551 | J17: 838 | K17: 1062 | L17: 623 | M17: -1541 | N17: 1643 | O17: 1556 | P17: -381 | Q17: 2057 | T17: -85 | U17: -129 | V17: 7 | W17: -1334 | X17: 880 | Y17: -19 | Z17: 586 | AA17: 196 | AB17: 579 | AC17: 929 | AD17: 632 | AE17: -584 | AF17: 648 | AG17: 472 | AH17: 501 | AI17: -2002 | AJ17: 1106 | AK17: -510 | AL17: -299 | AM17: 1761
D18: Share of income in joint ventures and associates | E18: 24 | F18: 179 | G18: 191 | H18: 230 | I18: 418 | J18: 200 | K18: 67 | L18: -168 | M18: -352 | N18: -951 | O18: 4443 | P18: -5628 | Q18: -4722 | T18: -438 | U18: -350 | V18: 422 | W18: 14 | X18: 2895 | Y18: -899 | Z18: -987 | AA18: -1960 | AB18: 161 | AC18: 6189 | AD18: -1463 | AE18: -444 | AF18: -1215 | AG18: -1434 | AH18: -1690 | AI18: -1289 | AJ18: -2089 | AK18: -247 | AL18: 80 | AM18: -2466
D19: Operating income | E19: 18 | F19: 1919 | G19: 2128 | H19: 6620 | I19: 11014 | J19: 14061 | K19: 14185 | L19: 14303 | M19: 8036 | N19: 20275 | O19: 22332 | P19: 19939 | Q19: 22318 | T19: 639 | U19: -1628 | V19: 4181 | W19: 4844 | X19: 8423 | Y19: 4815 | Z19: 3329 | AA19: 3708 | AB19: 6038 | AC19: 10801 | AD19: 2050 | AE19: 3443 | AF19: 5100 | AG19: 4993 | AH19: 4458 | AI19: 5388 | AJ19: 4706 | AK19: 7969 | AL19: 5790 | AM19: 3853
D21: Interest income and similar credits | E21: 118 | F21: 83 | G21: 147 | H21: 139 | I21: 216 | J21: 302 | K21: 408 | L21: 568 | M21: 548 | N21: 600 | O21: 852 | P21: 2495 | Q21: 2190 | T21: 160 | U21: 87 | V21: 112 | W21: 189 | X21: 169 | Y21: 130 | Z21: 138 | AA21: 163 | AB21: 165 | AC21: 139 | AD21: 211 | AE21: 337 | AF21: 499 | AG21: 598 | AH21: 658 | AI21: 740 | AJ21: 681 | AK21: 590 | AL21: 479 | AM21: 440
D22: Interest expenses and similar charges | E22: -494 | F22: -497 | G22: -955 | H22: -1120 | I22: -968 | J22: -830 | K22: -767 | L22: -1256 | M22: -1208 | N22: -1057 | O22: -837 | P22: -772 | Q22: -1164 | T22: -300 | U22: -288 | V22: -275 | W22: -345 | X22: -285 | Y22: -292 | Z22: -265 | AA22: -215 | AB22: -205 | AC22: -212 | AD22: -191 | AE22: -228 | AF22: -200 | AG22: -192 | AH22: -190 | AI22: -190 | AJ22: -444 | AK22: -602 | AL22: -385 | AM22: -324
D23: Other financial income and expenses | E23: -557 | F23: -373 | G23: -165 | H23: -250 | I23: -741 | J23: -386 | K23: -909 | L23: -447 | M23: 1690 | N23: -1058 | O23: -1532 | P23: -802 | Q23: -625 | T23: 184 | U23: -171 | V23: -186 | W23: 1863 | X23: -698 | Y23: -285 | Z23: -110 | AA23: 35 | AB23: -215 | AC23: -729 | AD23: -153 | AE23: -436 | AF23: -15 | AG23: -26 | AH23: -204 | AI23: -557 | AJ23: 155 | AK23: -135 | AL23: 170 | AM23: -224
D24: Income before tax | E24: -915 | F24: 1132 | G24: 1155 | H24: 5389 | I24: 9521 | J24: 13147 | K24: 12917 | L24: 13168 | M24: 9066 | N24: 18760 | O24: 20815 | P24: 20860 | Q24: 22719 | T24: 683 | U24: -2000 | V24: 3832 | W24: 6551 | X24: 7609 | Y24: 4368 | Z24: 3092 | AA24: 3691 | AB24: 5783 | AC24: 9999 | AD24: 1917 | AE24: 3116 | AF24: 5384 | AG24: 5373 | AH24: 4722 | AI24: 5381 | AJ24: 5098 | AK24: 7822 | AL24: 6054 | AM24: 3745
D26: Income tax | E26: 435 | F26: -172 | G26: -647 | H26: -913 | I26: -2061 | J26: -2922 | K26: -3136 | L26: -3565 | M26: -1758 | N26: -4583 | O26: -3812 | P26: -6794 | Q26: -6785 | T26: -87 | U26: 233 | V26: -899 | W26: -1005 | X26: -1146 | Y26: -1204 | Z26: -800 | AA26: -1433 | AB26: -1280 | AC26: -1021 | AD26: -1252 | AE26: -259 | AF26: -1409 | AG26: -1833 | AH26: -1503 | AI26: -2049 | AJ26: -1511 | AK26: -2168 | AL26: -1698 | AM26: -1408
D27: Net income for the period | E27: -480 | F27: 960 | G27: 508 | H27: 4476 | I27: 7460 | J27: 10225 | K27: 9781 | L27: 9603 | M27: 7308 | N27: 14177 | O27: 17003 | P27: 14066 | Q27: 15934 | T27: 596 | U27: -1767 | V27: 2933 | W27: 5546 | X27: 6463 | Y27: 3164 | Z27: 2292 | AA27: 2258 | AB27: 4503 | AC27: 8978 | AD27: 665 | AE27: 2857 | AF27: 3975 | AG27: 3540 | AH27: 3219 | AI27: 3332 | AJ27: 3587 | AK27: 5654 | AL27: 4356 | AM27: 2337
D29: Net income attributable to
D30: Owners of the parent company | E30: -530 | F30: 960 | G30: 540 | H30: 3130 | I30: 5944 | J30: 7960 | K30: 6840 | L30: 7115 | M30: 5594 | N30: 12546 | O30: 15577 | P30: 13053 | Q30: 15401 | T30: 586 | U30: -2323 | V30: 2553 | W30: 4778 | X30: 5742 | Y30: 2502 | Z30: 2187 | AA30: 2115 | AB30: 3853 | AC30: 8935 | AD30: 333 | AE30: 2456 | AF30: 3611 | AG30: 3332 | AH30: 3001 | AI30: 3109 | AJ30: 3342 | AK30: 5348 | AL30: 4208 | AM30: 2503
D31: Non-controlling interests | E31: 50 | F31: - | G31: -32 | H31: 1346 | I31: 1516 | J31: 2265 | K31: 2941 | L31: 2488 | M31: 1714 | N31: 1631 | O31: 1426 | P31: 1013 | Q31: 533 | T31: 10 | U31: 556 | V31: 380 | W31: 768 | X31: 721 | Y31: 662 | Z31: 105 | AA31: 143 | AB31: 650 | AC31: 43 | AD31: 332 | AE31: 401 | AF31: 364 | AG31: 208 | AH31: 218 | AI31: 223 | AJ31: 245 | AK31: 306 | AL31: 148 | AM31: -166
E32: -480 | F32: 960 | G32: 508 | H32: 4476 | I32: 7460 | J32: 10225 | K32: 9781 | L32: 9603 | M32: 7308 | N32: 14177 | O32: 17003 | P32: 14066 | Q32: 15934 | T32: 596 | U32: -1767 | V32: 2933 | W32: 5546 | X32: 6463 | Y32: 3164 | Z32: 2292 | AA32: 2258 | AB32: 4503 | AC32: 8978 | AD32: 665 | AE32: 2857 | AF32: 3975 | AG32: 3540 | AH32: 3219 | AI32: 3332 | AJ32: 3587 | AK32: 5654 | AL32: 4356 | AM32: 2337
D36: 1) Not restated after the acquisitions of the Chinese industrial entities in 2015.
D37: 2) The comparative figures for 2014 are restated to include the new Volvo Car Group structure including the acquired Chinese industrial entities. For further descriptions refer to the Volvo Car Group’s annual report 2015.
D38: 3)2015 and 2016 year's net revenue has been restated to hedged currency rates.
D39: 4) In 2017, sold licenses have been reclassified from Other Operating Income to Net Revenue. The comparative periods (2015 and 2016) has been restated.
D40: 5) In 2017, costs have been reclassified from cost of sales to research and development. The comparative periods (2015 and 2016) has been restated.
D41: 6) In 2018, there has been a change related to sale of certain cars accounted for as operating leasing. The comparative periods 2017, 2016 and 2015 have been changed accordingly, reducing net revenue and cost of sales. The change has not had any effect on gross income.
D42: 7) In Q4 2021, market valuation has been moved from financial expense to financial income, affecting only the isolated quarter.
D43: 8) In 2022, there has been a change in the elimination of internal profit related to sale of digital services from VCC to other entities within the Group. This change has resulted in a decrease of cost of sales, research and development expenses and selling expenses against an increase of administrative expenses. The comparative figures have been adjusted accordingly, but only for 2021, due to the reclassification for previous periods not having a material impact. The reclassification has no impact on EBIT.
D44: 9) In 2022, a prior period error was identified with regards to the recognition of a government grant in China. The comparative figures have been adjusted accordingly affecting 2020.

Sheet Revenue Geographical
D1: Revenue Geographical
D9: MSEK | E9: Q1 2020 | F9: Q2 2020 | G9: Q3 2020 | H9: Q4 2020 | I9: Q1 2021 | J9: Q2 2021 | K9: Q3 2021 | L9: Q4 2021 | M9: Q1 2022 | N9: Q2 2022 | O9: Q3 2022 | P9: Q4 2022 | Q9: Q1 2023 | R9: Q2 2023 | S9: Q3 2023 | T9: Q4 2023 | U9: Q1 2024 | V9: Q2 2024 | W9: Q3 2024 | X9: Q4 2024
D10: China | E10: 7372 | F10: 16910 | G10: 17294 | H10: 19660 | I10: 16628 | J10: 17707 | K10: 12638 | L10: 16553 | M10: 17409 | N10: 14012 | O10: 21113 | P10: 18390 | Q10: 16585 | R10: 19640 | S10: 18811 | T10: 18509 | U10: 14901 | V10: 17310 | W10: 13033 | X10: 18438
D11: US | E11: 8680 | F11: 7813 | G11: 9909 | H11: 14179 | I11: 11006 | J11: 12765 | K11: 13404 | L11: 14840 | M11: 11321 | N11: 16247 | O11: 12900 | P11: 19602 | Q11: 19490 | R11: 19672 | S11: 16952 | T11: 19058 | U11: 15182 | V11: 17330 | W11: 17700 | X11: 19284
D12: Europe | E12: 31559 | F12: 23227 | G12: 28454 | H12: 38664 | I12: 30738 | J12: 30062 | K12: 24086 | L12: 36141 | M12: 34139 | N12: 28429 | O12: 33596 | P12: 47986 | Q12: 44102 | R12: 46489 | S12: 39960 | T12: 54343 | U12: 51555 | V12: 50675 | W12: 47400 | X12: 59284
D13: of which Sweden1) | E13: 6840 | F13: 5426 | G13: 5905 | H13: 7375 | I13: 7529 | J13: 6361 | K13: 5185 | L13: 9170 | M13: 10401 | N13: 7838 | O13: 11299 | P13: 15385 | Q13: 11575 | R13: 13169 | S13: 10382 | T13: 11904 | U13: 9484 | V13: 11438 | W13: 12887 | X13: 14287
D14: of which United Kingdom | E14: 4874 | F14: 2073 | G14: 4145 | H14: 4774 | I14: 3501 | J14: 3733 | K14: 3772 | L14: 4604 | M14: 3494 | N14: 3623 | O14: 3419 | P14: 5623 | Q14: 4575 | R14: 5504 | S14: 4663 | T14: 6919 | U14: 5935 | V14: 7550 | W14: 8477 | X14: 9971
D15: of which Germany | E15: 5084 | F15: 3867 | G15: 3822 | H15: 5546 | I15: 3724 | J15: 3748 | K15: 4019 | L15: 5332 | M15: 4127 | N15: 4354 | O15: 4205 | P15: 6329 | Q15: 5434 | R15: 5360 | S15: 5681 | T15: 8467 | U15: 7401 | V15: 6450 | W15: 6973 | X15: 8476
D16: Other markets | E16: 8906 | F16: 7292 | G16: 10106 | H16: 12808 | I16: 10221 | J16: 12004 | K16: 10710 | L16: 12542 | M16: 11400 | N16: 12612 | O16: 11720 | P16: 17269 | Q16: 15528 | R16: 16351 | S16: 16322 | T16: 17531 | U16: 12240 | V16: 16139 | W16: 14650 | X16: 15113
D17: of which Turkey | S17: - | T17: - | U17: - | V17: - | W17: - | X17: 2440
D18: of which South Korea | E18: 1346 | F18: 1250 | G18: 683 | H18: 1780 | I18: 1507 | J18: 1580 | K18: 1264 | L18: 1542 | M18: 1463 | N18: 1424 | O18: 920 | P18: 2217 | Q18: 2176 | R18: 1994 | S18: 1941 | T18: 2225 | U18: 1521 | V18: 1987 | W18: 1690 | X18: 1912
D19: of which Japan | E19: 2143 | F19: 1612 | G19: 1801 | H19: 1789 | I19: 1775 | J19: 1958 | K19: 1630 | L19: 2114 | M19: 1860 | N19: 2263 | O19: 1774 | P19: 2442 | Q19: 2286 | R19: 2216 | S19: 1798 | T19: 1373 | U19: 1359 | V19: 1466 | W19: 1576 | X19: -
D20: Total | E20: 56517 | F20: 55242 | G20: 65763 | H20: 85311 | I20: 68593 | J20: 72538 | K20: 60838 | L20: 80076 | M20: 74269 | N20: 71300 | O20: 79329 | P20: 105247 | Q20: 95705 | R20: 102152 | S20: 92045 | T20: 109441 | U20: 93878 | V20: 101454 | W20: 92783 | X20: 112119
D23: 1) Includes the Contract manufacturing sales channel.

Sheet BS - Assets
D1: BS - Assets
D9: MSEK | E9: Full Year 20121) | F9: Full Year 20131) | G9: Full Year 20142) | H9: Full Year 2015 | I9: Full Year 2016 | J9: Full Year 2017 | K9: Full year 2018 | L9: Full year 2019 | M9: Full year 20203)4)5) | N9: Full year 20213)4)5) | O9: Full year 2022 | P9: Full year 2023 | Q9: Full year 2024
D10: ASSETS
D11: Non-current assets
D12: Intangible assets | E12: 15666 | F12: 17271 | G12: 20649 | H12: 22834 | I12: 25368 | J12: 29157 | K12: 29626 | L12: 32786 | M12: 37168 | N12: 43840 | O12: 56994 | P12: 72104 | Q12: 83781
D13: Tangible assets3) | E13: 25654 | F13: 25653 | G13: 36122 | H13: 37428 | I13: 45468 | J13: 55245 | K13: 61208 | L13: 69738 | M13: 62455 | N13: 71415 | O13: 77252 | P13: 84113 | Q13: 107124
D14: Assets held under operating leases3) | E14: 3542 | F14: 189 | G14: 1942 | H14: 2172 | I14: 2483 | J14: 2577 | K14: 2523 | L14: 3243 | M14: - | N14: - | O14: - | P14: - | Q14: -
D15: Receivables on parent company | E15: - | F15: - | G15: - | H15: - | I15: 54 | J15: 54 | K15: 54 | L15: 54 | M15: - | N15: - | O15: - | P15: - | Q15: -
D16: Investments in joint ventures and associates | E16: 550 | F16: 1159 | G16: 612 | H16: 701 | I16: 2498 | J16: 5480 | K16: 7003 | L16: 9211 | M16: 9997 | N16: 6931 | O16: 15599 | P16: 14142 | Q16: 8998
D17: Other long-term securities holdings | E17: 10 | F17: 10 | G17: 13 | H17: 15 | I17: 79 | J17: 80 | K17: 190 | L17: 296 | M17: 2449 | N17: 1765 | O17: 4353 | P17: 12066 | Q17: 12753
D18: Deferred tax assets | E18: 1820 | F18: 2165 | G18: 3107 | H18: 3841 | I18: 4112 | J18: 4557.7034 | K18: 6586 | L18: 7275 | M18: 7164 | N18: 7367 | O18: 9131 | P18: 10135 | Q18: 10982
D19: Other non-current interest-bearing receivables | E19: - | F19: - | G19: - | H19: - | I19: - | J19: - | K19: - | L19: - | M19: - | N19: 5046 | O19: 3354 | P19: 1327 | Q19: 1440
D20: Non-current derivate assets4) | E20: - | F20: - | G20: - | H20: 54 | I20: - | J20: - | K20: - | L20: - | M20: 1277 | N20: 169 | O20: 1128 | P20: 2094 | Q20: 283
D21: Other non-current assets4) | E21: 734 | F21: 1077 | G21: 11656 | H21: 1326 | I21: 2013 | J21: 3704 | K21: 2982 | L21: 3253 | M21: 3481 | N21: 4863 | O21: 3994 | P21: 3426 | Q21: 4262
D22: Total non-current assets | E22: 47976 | F22: 49225 | G22: 74101 | H22: 68317 | I22: 82075 | J22: 100854.7 | K22: 110172 | L22: 125856 | M22: 123991 | N22: 141396 | O22: 171805 | P22: 199407 | Q22: 229623
D24: Current assets
D25: Inventories | E25: 11812 | F25: 14416 | G25: 17724 | H25: 20306 | I25: 21198 | J25: 30665 | K25: 35163 | L25: 38911 | M25: 35513 | N25: 36603 | O25: 46951 | P25: 57058 | Q25: 62455
D26: Accounts receivable | E26: 4735 | F26: 5618 | G26: 7674 | H26: 8805 | I26: 8717 | J26: 10832 | K26: 13704 | L26: 13243 | M26: 14776 | N26: 18553 | O26: 25239 | P26: 19284 | Q26: 22780
D27: Receivables on parent company | E27: - | F27: - | G27: - | H27: 54 | I27: - | J27: - | K27: - | L27: - | M27: - | N27: - | O27: - | P27: - | Q27: -
D28: Current tax assets | E28: 87 | F28: 97 | G28: 355 | H28: 307 | I28: 293 | J28: 463 | K28: 573 | L28: 987 | M28: 886 | N28: 951 | O28: 1763 | P28: 997 | Q28: 1854
D29: Current derivate assets4) | E29: - | F29: - | G29: - | H29: 54 | I29: - | J29: - | K29: - | L29: - | M29: 718 | N29: 824 | O29: 1769 | P29: 1988 | Q29: 485
D30: Other current assets4) | E30: 2587 | F30: 2781 | G30: 5332 | H30: 5393 | I30: 5757 | J30: 7955 | K30: 9875 | L30: 8855 | M30: 8434 | N30: 10860 | O30: 16239 | P30: 19849 | Q30: 14665
D31: Marketable securities | E31: - | F31: 88 | G31: 1047 | H31: 3512 | I31: 4738 | J31: 3992 | K31: 1577 | L31: 3518 | M31: 8087 | N31: 7996 | O31: 3415 | P31: 9918 | Q31: -
D32: Cash and cash equivalents | E32: 9607 | F32: 15372 | G32: 17002 | H32: 25623 | I32: 38635 | J32: 35402 | K32: 40170 | L32: 51997 | M32: 61592 | N32: 62265 | O32: 63743 | P32: 47861 | Q32: 56373
D33: Assets held for sale | E33: - | F33: - | G33: - | H33: - | I33: - | J33: - | K33: - | L33: - | M33: 7849 | N33: 3910 | O33: - | P33: - | Q33: -
D34: Total current assets | E34: 28828 | F34: 38372 | G34: 49134 | H34: 64000 | I34: 79338 | J34: 89309 | K34: 101062 | L34: 117511 | M34: 137855 | N34: 141962 | O34: 159119 | P34: 156955 | Q34: 158612
D36: TOTAL ASSETS | E36: 76804 | F36: 87597 | G36: 123235 | H36: 132317 | I36: 161413 | J36: 190163.7 | K36: 211234 | L36: 243367 | M36: 261846 | N36: 283358 | O36: 330924 | P36: 356362 | Q36: 388235
D40: 1) Not restated after the acquisitions of the Chinese industrial entities in 2015.
D41: 2) The comparative figures for 2014 are restated to include the new Volvo Car Group structure including the acquired Chinese industrial entities. For further descriptions refer to the Volvo Car Group’s annual report 2015.
D42: 3) From 2021, Assets held under operating leases are reported as a part of Tangible assets (previously called Property, Plant and Equipment). Comparative figures for 2020 have been adjusted accordingly.
D43: 4) From 2021, Derivative assets and liabilities are reported on separate lines (previously included in Other assets/liabilities). Comparative figures for 2020 have been adjusted accordingly.
D44: 5) In 2022 a prior period error was identified with regards to the recognition of government grant in China. Adjustments have been made for 2020 but do however impact the in- and outgoing balances of 2021.

Sheet BS - Equity & Liabilities
D1: BS - Equity & Liabilities
D9: MSEK | E9: Full Year 20121) | F9: Full Year 20131) | G9: Full Year 20142) | H9: Full Year 2015 | I9: Full Year 2016 | J9: Full Year 2017 | K9: Full year 2018 | L9: Full year 2019 | M9: Full year 20203) | N9: Full year 20213) | O9: Full year 2022 | P9: Full year 2023 | Q9: Full year 2024
D10: Equity
D11: Equity attributable to owners of the parent company | E11: 21901 | F11: 24638 | G11: 32804 | H11: 32550 | I11: 39536 | J11: 48729 | K11: 52873 | L11: 53883 | M11: 59179 | N11: 90185 | O11: 113947 | P11: 126371 | Q11: 137461
D12: Non-controlling interests | E12: - | F12: - | G12: 1464 | H12: 2085 | I12: 3774 | J12: 5931 | K12: 8378 | L12: 9765 | M12: 10773 | N12: 4327 | O12: 3331 | P12: 4114 | Q12: 4738
D13: Total equity | E13: 21901 | F13: 24638 | G13: 34268 | H13: 34635 | I13: 43310 | J13: 54660 | K13: 61251 | L13: 63648 | M13: 69952 | N13: 94512 | O13: 117278 | P13: 130485 | Q13: 142199
D15: Non-current liabilities
D16: Provisions for post-employment benefits | E16: 5492 | F16: 3641 | G16: 6186 | H16: 4701 | I16: 6348 | J16: 6525 | K16: 8425 | L16: 12583 | M16: 14187 | N16: 11961 | O16: 6883 | P16: 7610 | Q16: 8111
D17: Deferred tax liabilities | E17: 1556 | F17: 1759 | G17: 3337 | H17: 1768 | I17: 1209 | J17: 1977 | K17: 1688 | L17: 975 | M17: 1044 | N17: 2340 | O17: 5392 | P17: 8293 | Q17: 11080
D18: Other non-current provisions | E18: 5911 | F18: 5463 | G18: 1660 | H18: 2111 | I18: 2704 | J18: 4962 | K18: 6189 | L18: 7291 | M18: 8155 | N18: 8623 | O18: 8398 | P18: 7582 | Q18: 9501
D19: Non-current liabilities to credit institutions | E19: 7057 | F19: 12033 | G19: 17345 | H19: 15168 | I19: 13910 | J19: 6622 | K19: 8273 | L19: 4489 | M19: 5882 | N19: 2543 | O19: 3096 | P19: 4562 | Q19: 3885
D20: Non-current bond loans | E20: - | F20: - | G20: - | H20: - | I20: 7699 | J20: 12735 | K20: 13200 | L20: 21643 | M20: 20950 | N20: 18401 | O20: 22959 | P20: 18087 | Q20: 18826
D21: Non-current contract liabilities to customers | E21: - | F21: - | G21: 4554 | H21: 4332 | I21: 4662 | J21: 3662 | K21: 4184 | L21: 5210 | M21: 5630 | N21: 6967 | O21: 7144 | P21: 8148 | Q21: 10755
D22: Liabilities to parent company | E22: - | F22: - | G22: 1143 | H22: - | I22: - | J22: - | K22: - | L22: - | M22: - | N22: - | O22: - | P22: - | Q22: -
D23: Other non-current interest-bearing liabilities | E23: - | F23: - | G23: - | H23: - | I23: - | J23: - | K23: - | L23: 5076 | M23: 4815 | N23: 5509 | O23: 4845 | P23: 4790 | Q23: 7745
D24: Non-current derivative liabilities3) | E24: - | F24: - | G24: - | H24: - | I24: - | J24: - | K24: - | L24: - | M24: 300 | N24: 348 | O24: 825 | P24: 424 | Q24: 1252
D25: Other non-current liabilities3) | E25: 1057 | F25: 1212 | G25: 1244 | H25: 2393 | I25: 5447 | J25: 2636 | K25: 4609 | L25: 6471 | M25: 4577 | N25: 6039 | O25: 4726 | P25: 5385 | Q25: 5298
D26: Total non-current liabilities | E26: 21073 | F26: 24108 | G26: 35469 | H26: 30473 | I26: 41979 | J26: 39119 | K26: 46568 | L26: 63738 | M26: 65540 | N26: 62731 | O26: 64268 | P26: 64881 | Q26: 76453
D28: Current liabilities
D29: Current provisions | E29: 7182 | F29: 8169 | G29: 3645 | H29: 4018 | I29: 5487 | J29: 6513 | K29: 6936 | L29: 8357 | M29: 8530 | N29: 8607 | O29: 9051 | P29: 13117 | Q29: 11379
D30: Current liabilities to credit institutions | E30: 310 | F30: 820 | G30: 1560 | H30: 6246 | I30: 2813 | J30: 7426 | K30: 2175 | L30: 4105 | M30: 2512 | N30: 4471 | O30: 755 | P30: 937 | Q30: 1059
D31: Current bond loans | E31: - | F31: - | G31: - | H31: - | I31: - | J31: - | K31: - | L31: - | M31: 5017 | N31: - | O31: 2000 | P31: 6660 | Q31: 5723
D32: Current contract liabilities to customers | E32: 187 | F32: 317 | G32: 7690 | H32: 9749 | I32: 11453 | J32: 14507 | K32: 17511 | L32: 20478 | M32: 21842 | N32: 22929 | O32: 26094 | P32: 30817 | Q32: 34997
D33: Accounts payable | E33: 12626 | F33: 13632 | G33: 18563 | H33: 26282 | I33: 30508 | J33: 38536 | K33: 43633 | L33: 44876 | M33: 46635 | N33: 48283 | O33: 68913 | P33: 62304 | Q33: 56479
D34: Current tax liabilities | E34: 365 | F34: 658 | G34: 627 | H34: 446 | I34: 626 | J34: 1380 | K34: 1645 | L34: 1302 | M34: 1486 | N34: 1402 | O34: 1566 | P34: 1607 | Q34: 1246
D35: Liabilities to parent company | E35: - | F35: - | G35: 1651 | H35: - | I35: - | J35: - | K35: - | L35: - | M35: - | N35: - | O35: - | P35: - | Q35: -
D36: Other current interest-bearing liabilities | E36: - | F36: - | G36: - | H36: - | I36: - | J36: - | K36: - | L36: 1073 | M36: 1160 | N36: 1462 | O36: 1500 | P36: 1242 | Q36: 2490
D37: Current derivative liabilities3) | F37: - | G37: - | H37: - | I37: - | J37: - | K37: - | L37: - | M37: 1705 | N37: 2312 | O37: 1809 | P37: 1055 | Q37: 2890
D38: Other current liabilities3) | E38: 13160 | F38: 15255 | G38: 19762 | H38: 20468 | I38: 25237 | J38: 28023 | K38: 31515 | L38: 35790 | M38: 35718 | N38: 34524 | O38: 37690 | P38: 43257 | Q38: 53320
D39: Liabilities held for sale | E39: - | F39: - | G39: - | H39: - | I39: - | J39: - | K39: - | L39: - | M39: 1749 | N39: 2125 | O39: - | P39: - | Q39: -
D40: Total current liabilities | E40: 33830 | F40: 38851 | G40: 53498 | H40: 67209 | I40: 76124 | J40: 96385 | K40: 103415 | L40: 115981 | M40: 126354 | N40: 126115 | O40: 149378 | P40: 160996 | Q40: 169583
D42: TOTAL EQUITY & LIABILITIES | E42: 76804 | F42: 87597 | G42: 123235 | H42: 132317 | I42: 161413 | J42: 190164 | K42: 211234 | L42: 243367 | M42: 261846 | N42: 283358 | O42: 330924 | P42: 356362 | Q42: 388235
D46: 1) Not restated after the acquisitions of the Chinese industrial entities in 2015.
D47: 2) The comparative figures for 2014 are restated to include the new Volvo Car Group structure including the acquired Chinese industrial entities. For further descriptions refer to the Volvo Car Group’s annual report 2015.
D48: 3) From 2021, Derivative assets and liabilities are reported on separate lines (previously included in Other assets/liabilities). Comparative figures for 2020 have been adjusted accordingly.
D49: 4) In 2022 a prior period error was identified with regards to the recognition of government grant in China. Adjustments have been made for 2020 but do however impact the in- and outgoing balances of 2021.

Sheet Cash Flow
D1: Cash Flow
E8: Yearly | S8: Quarterly
D9: MSEK | E9: Full Year 20121) | F9: Full Year 20131) | G9: Full Year 20142) | H9: Full Year 2015 | I9: Full Year 2016 | J9: Full Year 2017 | K9: Full Year 2018 | L9: Full Year 2019 | M9: Full year 20203)4)6) | N9: Full year 20213)4) | O9: Full year 2022 | P9: Full year 2023 | Q9: Full year 2024 | S9: Q1 2020 | T9: Q2 2020 | U9: Q3 20206) | V9: Q4 20206) | W9: Q1 2021 | X9: Q2 2021 | Y9: Q3 2021 | Z9: Q4 2021 | AA9: Q1 2022 | AB9: Q2 2022 | AC9: Q3 2022 | AD9: Q4 2022 | AE9: Q1 2023 | AF9: Q2 2023 | AG9: Q3 2023 | AH9: Q4 2023 | AI9: Q1 2024 | AJ9: Q2 2024 | AK9: Q3 2024 | AL9: Q4 2024
D10: OPERATING ACTIVITIES
D11: Operating income | E11: 18 | F11: 1919 | G11: 2128 | H11: 6619.6757 | I11: 11014 | J11: 14061 | K11: 14185 | L11: 14303 | M11: 8036 | N11: 20275 | O11: 22332 | P11: 19939 | Q11: 22318 | S11: 639 | T11: -1628 | U11: 4181 | V11: 4844 | W11: 8423 | X11: 4815 | Y11: 3329 | Z11: 3708 | AA11: 6038 | AB11: 10801 | AC11: 2050 | AD11: 3443 | AE11: 5100 | AF11: 4993 | AG11: 4458 | AH11: 5388 | AI11: 4706 | AJ11: 7969 | AK11: 5790 | AL11: 3853
D12: Depreciation and amortisation of non-current assets | E12: 8016 | F12: 7138 | G12: 7363 | H12: 9399 | I12: 10527 | J12: 12098 | K12: 13213 | L12: 15548 | M12: =14449+93 -> 14542 | N12: 15005 | O12: 16091 | P12: 17449 | Q12: 22730 | S12: 3853 | T12: 3955 | U12: 3649 | V12: 3085 | W12: 4134 | X12: 3546 | Y12: 3608 | Z12: 3717 | AA12: 3985 | AB12: 4020 | AC12: 4005 | AD12: 4081 | AE12: 4129 | AF12: 4205 | AG12: 4193 | AH12: 4922 | AI12: 5418 | AJ12: 5975 | AK12: 4579 | AL12: 6758
D13: Dividends received from joint ventures and associates | E13: - | F13: - | G13: - | H13: - | I13: - | J13: - | K13: - | L13: - | M13: 333 | N13: 1991 | O13: 72 | P13: 88 | Q13: 213 | S13: - | T13: 7 | U13: 326 | V13: - | W13: 1175 | X13: 112 | Y13: 704 | Z13: - | AA13: - | AB13: 72 | AC13: - | AD13: - | AE13: 4 | AF13: 84 | AG13: - | AH13: - | AI13: 3 | AJ13: 110 | AK13: 100 | AL13: -
D14: Interest and similar items received | E14: 120 | F14: 87 | G14: 149 | H14: 141.349 | I14: 218 | J14: 303 | K14: 408 | L14: 572 | M14: 550 | N14: 602 | O14: 1065 | P14: 2495 | Q14: 2190 | S14: 157 | T14: 92 | U14: 111 | V14: 190 | W14: 1364 | X14: -1023 | Y14: 98 | Z14: 163 | AA14: 165 | AB14: 281 | AC14: 362 | AD14: 257 | AE14: 499 | AF14: 598 | AG14: 658 | AH14: 740 | AI14: 681 | AJ14: 590 | AK14: 479 | AL14: 440
D15: Interest and similar items paid | E15: -423 | F15: -433 | G15: -875 | H15: -1021.6322 | I15: -953 | J15: -1016 | K15: -818 | L15: -854 | M15: -1268 | N15: -1139 | O15: -1351 | P15: -1710 | Q15: -1623 | S15: -239 | T15: -418 | U15: -133 | V15: -478 | W15: -1517 | X15: 809 | Y15: -134 | Z15: -297 | AA15: -239 | AB15: -455 | AC15: -288 | AD15: -369 | AE15: -276 | AF15: -513 | AG15: -253 | AH15: -668 | AI15: -715 | AJ15: -498 | AK15: -156 | AL15: -254
D16: Other financial items | E16: -85 | F16: -80 | G16: -40 | H16: -176 | I16: -418 | J16: -383 | K16: -203 | L16: -607 | M16: -437 | N16: -815 | O16: 206 | P16: 178 | Q16: -836 | S16: 16 | T16: -317 | U16: -44 | V16: -92 | W16: -101 | X16: -566 | Y16: -7 | Z16: -141 | AA16: 101 | AB16: 23 | AC16: 18 | AD16: 64 | AE16: 154 | AF16: -85 | AG16: -29 | AH16: 138 | AI16: -694 | AJ16: -43 | AK16: 9 | AL16: -108
D17: Income tax paid | E17: -928 | F17: -573 | G17: -1293 | H17: -1645 | I17: -1705 | J17: -3471 | K17: -4132 | L17: -4089 | M17: -2856 | N17: -3673 | O17: -4223 | P17: -4486 | Q17: -4448 | S17: -907 | T17: -804 | U17: -770 | V17: -375 | W17: -959 | X17: -1454 | Y17: -978 | Z17: -282 | AA17: -1360 | AB17: -706 | AC17: -1273 | AD17: -884 | AE17: -1243 | AF17: -1884 | AG17: -951 | AH17: -408 | AI17: -869 | AJ17: -1638 | AK17: -1259 | AL17: -682
D18: Adjustments for items not affecting cash flow | E18: -362 | F18: -281 | G18: -552 | H18: 123 | I18: 987 | J18: 587 | K18: 68 | L18: -2415 | M18: 3989 | N18: -750 | O18: -7135 | P18: 6087 | Q18: 2754 | S18: 1410 | T18: 1833 | U18: -481 | V18: 1227 | W18: -3670 | X18: 3200 | Y18: -31 | Z18: -249 | AA18: -1096 | AB18: -5897 | AC18: 57 | AD18: -231 | AE18: 332 | AF18: 3528 | AG18: 1039 | AH18: 1188 | AI18: 2674 | AJ18: 788 | AK18: -3233 | AL18: 2525
E19: 6356 | F19: 7777 | G19: 6880 | H19: 13440.393 | I19: 19670 | J19: 22179 | K19: 22721 | L19: 22458 | M19: =SUM(M11:M18) -> 22889 | N19: 31496 | O19: =SUM(O11:O18) -> 27057 | P19: 40040 | Q19: 43298 | S19: 4929 | T19: 2720 | U19: 6839 | V19: 8401 | W19: 8849 | X19: 9439 | Y19: 6589 | Z19: 6619 | AA19: 7594 | AB19: 8139 | AC19: 4931 | AD19: 6361 | AE19: =SUM(AE11:AE18) -> 8699 | AF19: 10926 | AG19: 9115 | AH19: 11300 | AI19: 11204 | AJ19: 13253 | AK19: 6309 | AL19: 12532
D21: Movements in working capital
D22: Change in inventories | E22: 1407 | F22: -349 | G22: -2272 | H22: -3056.4742 | I22: -1013 | J22: -10536 | K22: -3706 | L22: -3066 | M22: -454 | N22: 3643 | O22: -7348 | P22: -11341 | Q22: -2757 | S22: -7713 | T22: 3691 | U22: 179 | V22: 3389 | W22: -4691 | X22: 1666 | Y22: 4779 | Z22: 1889 | AA22: -3981 | AB22: -559 | AC22: -3995 | AD22: 1119 | AE22: -3932 | AF22: -3565 | AG22: -4549 | AH22: 705 | AI22: -13664 | AJ22: -10421 | AK22: 2903 | AL22: 18425
D23: Change in accounts receivable | E23: -928 | F23: -883 | G23: -2720 | H23: -993.81011 | I23: 730 | J23: -2069 | K23: -2627 | L23: 694 | M23: -2137 | N23: 2845 | O23: -776 | P23: 4750 | Q23: -1386 | S23: 513 | T23: -1720 | U23: 588 | V23: -1518 | W23: -1273 | X23: 153 | Y23: 2636 | Z23: 1329 | AA23: -5 | AB23: 5050 | AC23: -1170 | AD23: -4651 | AE23: 4178 | AF23: -4291 | AG23: 4315 | AH23: 548 | AI23: -6670 | AJ23: 1802 | AK23: 335 | AL23: 3147
D24: Change in accounts payable | E24: -2838 | F24: 1006 | G24: 4227 | H24: 7658 | I24: 4023 | J24: 8220 | K24: 4372 | L24: 1969 | M24: 5183 | N24: -3328 | O24: 18533 | P24: -2918 | Q24: -7539 | S24: -5327 | T24: -696 | U24: 6385 | V24: 4821 | W24: -2904 | X24: -4666 | Y24: -10442 | Z24: 14684 | AA24: -4773 | AB24: -1250 | AC24: 11012 | AD24: 13544 | AE24: -8948 | AF24: 4476 | AG24: -802 | AH24: 2356 | AI24: -1667 | AJ24: 6816 | AK24: -857 | AL24: -11831
D25: Change in items relating to repurchase commitments | E25: -1132 | F25: -47 | G25: -193 | H25: - | I25: - | J25: - | K25: - | L25: - | M25: - | N25: - | O25: - | P25: - | Q25: - | S25: - | T25: - | U25: - | V25: - | W25: - | X25: - | Y25: - | Z25: - | AA25: - | AB25: - | AC25: - | AD25: - | AE25: - | AF25: - | AG25: - | AH25: - | AI25: - | AJ25: - | AK25: - | AL25: -
D26: Change in provisions | E26: -858 | F26: 767 | G26: 2507 | H26: 779 | I26: 1558 | J26: 2398 | K26: -608 | L26: 926 | M26: -303 | N26: -1126 | O26: -4640 | P26: -1914 | Q26: -1905 | S26: -1042 | T26: -910 | U26: 318 | V26: 1331 | W26: 160 | X26: -33 | Y26: -1268 | Z26: 15 | AA26: -1764 | AB26: -2817 | AC26: -907 | AD26: 848 | AE26: 711 | AF26: -3794 | AG26: 472 | AH26: 697 | AI26: 969 | AJ26: -3226 | AK26: 2069 | AL26: -1717
D27: Change in contract liability to customers | E27: - | F27: - | G27: - | H27: 1837 | I27: 2034 | J27: 2054 | K27: 6093 | L27: 6503 | M27: 3872 | N27: 2239 | O27: 5941 | P27: 8707 | Q27: 8709 | S27: 19 | T27: 919 | U27: 677 | V27: 2257 | W27: -121 | X27: -566 | Y27: -501 | Z27: 3427 | AA27: -1487 | AB27: 772 | AC27: 3703 | AD27: 2953 | AE27: -172 | AF27: 4245 | AG27: 2058 | AH27: 2576 | AI27: -1100 | AJ27: 2219 | AK27: 788 | AL27: 6802
D28: Change in other working capital assets/liabilities | E28: 743 | F28: 590 | G28: 410 | H28: 3476 | I28: 285 | J28: 2687 | K28: 520 | L28: 2890 | M28: =4848+992 -> 5840 | N28: -5917 | O28: -5168 | P28: 5543 | Q28: 8952 | S28: -1259 | T28: 2410 | U28: 1408 | V28: 3281 | W28: -4208 | X28: 528 | Y28: -3679 | Z28: 1442 | AA28: 177 | AB28: -1964 | AC28: -174 | AD28: -3213 | AE28: -2916 | AF28: 8986 | AG28: -485 | AH28: -42 | AI28: 9991 | AJ28: 2336 | AK28: -2335 | AL28: -1040
D29: Cash flow from movements in working capital | E29: -3607 | F29: 1084 | G29: 1959 | H29: 9699.7157 | I29: 7617 | J29: 2754 | K29: 4044 | L29: 9916 | M29: =SUM(M22:M28) -> 12001 | N29: -1644 | O29: 6542 | P29: 2827 | Q29: 4074 | S29: -14809 | T29: 3694 | U29: 9555 | V29: 13561 | W29: -13037 | X29: -2918 | Y29: -8475 | Z29: 22786 | AA29: -11833 | AB29: -768 | AC29: 8469 | AD29: 10600 | AE29: -11079 | AF29: 6057 | AG29: 1009 | AH29: 6840 | AI29: -12141 | AJ29: -474 | AK29: 2903 | AL29: 13786
D30: Cash flow from operating activities | E30: 2749 | F30: 8861 | G30: 8839 | H30: 23140 | I30: 27287 | J30: 24933 | K30: 26765 | L30: 32374 | M30: =+M19+M29 -> 34890 | N30: 29852 | O30: 33599 | P30: 42867 | Q30: 47372 | S30: -9880 | T30: 6414 | U30: 16394 | V30: 21962 | W30: -4188 | X30: 6521 | Y30: -1886 | Z30: 29405 | AA30: -4239 | AB30: 7371 | AC30: 13400 | AD30: 16961 | AE30: -2380 | AF30: 16983 | AG30: 10124 | AH30: 18140 | AI30: -937 | AJ30: 12779 | AK30: 9212 | AL30: 26318
D32: INVESTING ACTIVITIES
D33: Investments in shares and participations, net | E33: -258 | F33: -520 | G33: 275 | H33: -2239 | I33: -1280 | J33: -2081 | K33: -1565 | L33: -235 | M33: - | N33: - | O33: - | P33: - | Q33: - | S33: - | T33: - | U33: - | V33: - | W33: - | X33: - | Y33: - | Z33: - | AA33: - | AB33: - | AC33: - | AD33: - | AE33: - | AF33: - | AG33: - | AH33: - | AI33: - | AJ33: - | AK33: - | AL33: -
D34: Investments in shares and participations | E34: - | F34: - | G34: - | H34: - | I34: - | J34: - | K34: - | L34: - | M34: -4589 | N34: -11518 | O34: =-7107-2490 -> -9597 | P34: -1151 | Q34: -1901 | S34: -298 | T34: -115 | U34: -33 | V34: -4143 | W34: 1422 | X34: -27 | Y34: -2348 | Z34: -10565 | AA34: -1160 | AB34: -6460 | AC34: -168 | AD34: -1209 | AE34: -3572 | AF34: -13.891111 | AG34: -273 | AH34: -331 | AI34: -546 | AJ34: -776 | AK34: -1041 | AL34: 462
D35: Capital repayments from shares and participations | E35: - | F35: - | G35: - | H35: - | I35: - | J35: - | K35: - | L35: - | M35: 464 | N35: 132 | O35: - | P35: - | Q35: - | S35: 51 | T35: 194 | U35: 104 | V35: 115 | W35: - | X35: 132 | Y35: - | Z35: - | AA35: - | AB35: - | AC35: - | AD35: - | AE35: - | AF35: - | AG35: - | AH35: - | AI35: - | AJ35: - | AK35: - | AL35: -
D36: Divestment in shares and participations | E36: - | F36: - | G36: - | H36: - | I36: - | J36: - | K36: - | L36: - | M36: - | N36: - | O36: 2290 | P36: -178 | Q36: -217 | S36: - | T36: - | U36: - | V36: - | W36: - | X36: - | Y36: - | Z36: - | AB36: 116 | AC36: - | AD36: 1774 | AE36: - | AF36: - | AG36: -178 | AH36: - | AI36: - | AJ36: -216.64033 | AK36: - | AL36: -
D37: Loans to affiliated companies | E37: - | F37: - | G37: - | H37: - | I37: - | J37: - | K37: - | L37: - | M37: - | N37: - | O37: - | P37: - | Q37: - | S37: - | T37: - | U37: -1803 | V37: - | W37: - | X37: - | Y37: - | Z37: - | AA37: - | AB37: - | AC37: -3096 | AD37: 3096 | AE37: - | AF37: - | AG37: - | AH37: - | AI37: -45 | AJ37: -14.359668 | AK37: -17 | AL37: -
D38: Repayment of loans from affiliated companies | E38: - | F38: - | G38: - | H38: - | I38: - | J38: - | K38: - | L38: - | M38: 1251 | N38: - | O38: - | P38: -11990 | Q38: -75 | S38: - | T38: - | U38: - | V38: 3054 | W38: - | X38: - | Y38: - | Z38: - | AA38: - | AB38: - | AC38: - | AD38: - | AE38: -75 | AF38: -6047.1089 | AG38: -535 | AH38: -2294 | AI38: - | AJ38: - | AK38: - | AL38: 1
D39: Dividends received from joint ventures and associates | E39: - | F39: - | G39: - | H39: 26 | I39: 5 | J39: 37 | K39: 240 | L39: 64 | M39: - | N39: - | O39: - | P39: - | Q39: - | S39: - | T39: - | U39: - | V39: - | W39: - | X39: - | Y39: - | Z39: - | AA39: - | AB39: - | AC39: - | AD39: - | AE39: - | AF39: - | AG39: - | AH39: - | AI39: - | AJ39: - | AK39: - | AL39: -
D40: Investments in intangible assets | E40: -3061 | F40: -4188 | G40: -5234 | H40: -4715 | I40: -6394 | J40: -9651 | K40: -7283 | L40: -9176 | M40: -8574 | N40: -11972 | O40: -18328 | P40: -20680 | Q40: -19774 | S40: -2383 | T40: -1835 | U40: -2139 | V40: -2217 | W40: -2496 | X40: -2852 | Y40: -2826 | Z40: -3798 | AA40: -3136 | AB40: -4187 | AC40: -4125 | AD40: -6974 | AE40: -5545 | AF40: -5394 | AG40: -4514 | AH40: -5227 | AI40: -5139 | AJ40: -5481 | AK40: -4075 | AL40: -5079
D41: Disposal of intangible assets | E41: - | F41: 500 | G41: - | H41: - | I41: - | J41: - | K41: - | L41: - | M41: - | N41: - | O41: - | P41: - | Q41: - | S41: - | T41: - | U41: - | V41: - | W41: - | X41: - | Y41: - | Z41: - | AA41: - | AB41: - | AC41: - | AD41: - | AE41: - | AF41: - | AG41: - | AH41: - | AI41: - | AJ41: - | AK41: - | AL41: -
D42: Investments in tangible assets | E42: -4466 | F42: -4714 | G42: -8646 | H42: -9241 | I42: -13095 | J42: -17037 | K42: -13574 | L42: -11807 | M42: =-9986-605 -> -10591 | N42: -11352 | O42: -13784 | P42: -18485 | Q42: -25259 | S42: -2992 | T42: -2116 | U42: -2466 | V42: -3017 | W42: -1660 | X42: -3813 | Y42: -2178 | Z42: -3701 | AA42: -3758 | AB42: -2179 | AC42: -2797 | AD42: -5050 | AE42: -5962 | AF42: -4825 | AG42: -3202 | AH42: -4496 | AI42: -5572 | AJ42: -6314 | AK42: -5091 | AL42: -8282
D43: Disposal of tangible assets5) | E43: 93 | F43: 66 | G43: - | H43: 263 | I43: - | J43: - | K43: 122 | L43: 353 | M43: 431 | N43: 123 | O43: 161 | P43: 642 | Q43: 981 | S43: 108 | T43: 49 | U43: 90.671 | V43: 183.329 | W43: 32 | X43: 30 | Y43: 11 | Z43: 50 | AA43: 21 | AB43: 24 | AC43: 48 | AD43: 68 | AE43: 85 | AF43: 56 | AG43: 232 | AH43: 269 | AI43: 38 | AJ43: 142 | AK43: 611 | AL43: 190
D44: Other | E44: 14 | F44: 104 | G44: - | H44: - | I44: -8 | J44: -1 | K44: - | L44: - | M44: - | N44: -150 | O44: -400 | P44: - | Q44: - | S44: - | T44: - | U44: - | V44: - | W44: - | X44: - | Y44: - | Z44: -150 | AA44: - | AB44: -285 | AC44: -25 | AD44: -90 | AE44: - | AF44: -75 | AG44: 75 | AH44: - | AI44: - | AJ44: - | AK44: - | AL44: -
D45: Cash flow from investing activities | E45: -7678 | F45: -8752 | G45: -13605 | H45: -15906 | I45: -20772 | J45: -28733 | K45: -22060 | L45: -20801 | M45: =SUM(M33:M44) -> -21608 | N45: -34737 | O45: -39658 | P45: -51842 | Q45: -46245 | S45: =SUM(S33:S44) -> -5514 | T45: =SUM(T33:T44) -> -3823 | U45: =SUM(U33:U44) -> -6246.329 | V45: -6024.671 | W45: =SUM(W33:W44) -> -2702 | X45: =SUM(X33:X44) -> -6530 | Y45: =SUM(Y33:Y44) -> -7341 | Z45: -18164 | AA45: -8033 | AB45: -12971 | AC45: -10163 | AD45: -8385 | AE45: -15069 | AF45: -16299 | AG45: -8395 | AH45: -12079 | AI45: -11264 | AJ45: -12660 | AK45: -9613 | AL45: -12708
D46: Cash flow from operating and investing activities | E46: -4929 | F46: 109 | G46: -4766 | H46: 7234 | I46: 6515 | J46: -3800 | K46: 4705 | L46: 11573 | M46: =+M30+M45 -> 13282 | N46: -4885 | O46: -6059 | P46: -8975 | Q46: 1127 | S46: -15394 | T46: 2591 | U46: 10148 | V46: 15937 | W46: -6890 | X46: -9 | Y46: -9227 | Z46: 11241 | AA46: -12272 | AB46: -5600 | AC46: 3237 | AD46: 8576 | AE46: -17449 | AF46: 684 | AG46: 1729 | AH46: 6061 | AI46: -12201 | AJ46: 119 | AK46: -401 | AL46: 13610
D48: FINANCING ACTIVITIES
D49: Proceeds from credit institutions | E49: 8063 | F49: 5336 | G49: 7270 | H49: 5935 | I49: 1696 | J49: 1291 | K49: 3087 | L49: 1361 | M49: 5011 | N49: 1579 | O49: 1040 | P49: 3970 | Q49: 199 | S49: 421 | T49: 4282 | U49: 194 | V49: 114 | W49: 211 | X49: 1241 | Y49: 125 | Z49: 2 | AA49: 65 | AB49: 959 | AC49: 7 | AD49: 9 | AE49: 776 | AF49: 809 | AG49: -39 | AH49: 2424 | AI49: 116 | AJ49: -55 | AK49: -27 | AL49: 165
D50: Proceeds from bond issuance | E50: - | F50: - | G50: - | H50: - | I50: 7579 | J50: 4914 | K50: - | L50: 8221 | M50: 5209 | N50: - | O50: 5260 | P50: 1500 | Q50: 5857 | S50: - | T50: - | U50: - | V50: 5209 | W50: - | X50: - | Y50: - | Z50: - | AA50: - | AB50: 5260 | AC50: - | AD50: - | AE50: 1500 | AF50: - | AG50: - | AH50: - | AI50: - | AJ50: 5857 | AK50: - | AL50: -
D51: Acquisition of treasury shares | E51: - | F51: - | G51: - | H51: - | I51: - | J51: - | K51: - | L51: - | M51: - | N51: - | O51: - | P51: - | Q51: -190 | S51: - | T51: - | U51: - | V51: - | W51: - | X51: - | Y51: - | Z51: - | AA51: - | AB51: - | AC51: - | AD51: - | AE51: - | AF51: - | AG51: - | AH51: - | AI51: - | AJ51: - | AK51: -190 | AL51: -
D52: New share issue | E52: - | F52: - | G52: - | H52: - | I52: - | J52: - | K52: - | L52: - | M52: - | N52: 20807 | O52: - | P52: - | Q52: - | S52: - | T52: - | U52: - | V52: - | W52: - | X52: - | Y52: 907 | Z52: 19900 | AA52: - | AB52: - | AC52: - | AD52: - | AE52: - | AF52: - | AG52: - | AH52: - | AI52: - | AJ52: - | AK52: - | AL52: -
D53: Repayment of bond | E53: - | F53: - | G53: - | H53: - | I53: - | J53: - | K53: - | L53: - | M53: - | N53: -8064 | O53: - | P53: -2000 | Q53: -6936 | S53: - | T53: - | U53: - | V53: - | W53: - | X53: -5065 | Y53: - | Z53: -2999 | AA53: - | AB53: - | AC53: - | AD53: - | AE53: -2000 | AF53: - | AG53: - | AH53: - | AI53: - | AJ53: -6936 | AL53: -
D54: Repayment of liabilities to credit institutions | E54: -7251 | F54: -45 | G54: -5101 | H54: -6626 | I54: -7634 | J54: -3658 | K54: -7354 | L54: -3553 | M54: -4612 | N54: -2957 | O54: -4530 | P54: -673 | Q54: -862 | S54: -375 | T54: -2677 | U54: -448 | V54: -1112 | W54: -329 | X54: -1029 | Y54: -369 | Z54: -1230 | AA54: -4 | AB54: -4288 | AC54: 13 | AD54: -251 | AE54: - | AF54: -376 | AG54: 17 | AH54: -314 | AI54: -188 | AJ54: -315 | AK54: -59 | AL54: -300
D55: Repayment of interest bearing liabilities | E55: - | F55: - | G55: - | H55: - | I55: - | J55: - | K55: - | L55: -1356 | M55: -1350 | N55: -1450 | O55: -1711 | P55: -1747 | Q55: -2053 | S55: -346 | T55: -334 | U55: -322 | V55: -348 | W55: -334 | X55: -343 | Y55: -388 | Z55: -385 | AA55: -407 | AB55: -393 | AC55: -401 | AD55: -510 | AE55: -429 | AF55: -424 | AG55: -423 | AH55: -471 | AI55: -420 | AJ55: -499 | AK55: -526 | AL55: -608
D56: Proceeds from issuance of preference shares | E56: - | F56: - | G56: - | H56: - | I56: 4979 | J56: -82 | K56: - | L56: 5011 | M56: - | N56: - | O56: - | P56: - | Q56: - | S56: - | T56: - | U56: - | V56: - | W56: - | X56: - | Y56: - | Z56: - | AA56: - | AB56: - | AC56: - | AD56: - | AE56: - | AF56: - | AG56: - | AH56: - | AI56: - | AJ56: - | AK56: - | AL56: -
D57: Redemption of preference shares | E57: - | F57: - | G57: - | H57: - | I57: - | J57: - | K57: - | L57: -5745 | M57: - | N57: - | O57: - | P57: - | Q57: - | S57: - | T57: - | U57: - | V57: - | W57: - | X57: - | Y57: - | Z57: - | AA57: - | AB57: - | AC57: - | AD57: - | AE57: - | AF57: - | AG57: - | AH57: - | AI57: - | AJ57: - | AK57: - | AL57: -
D58: Dividend paid to shareholders and/or non-controlling interests | E58: - | F58: - | G58: - | H58: - | I58: - | J58: -2188 | K58: -67 | L58: -2897 | M58: -4 | N58: -10462 | O58: -846 | P58: - | Q58: - | S58: - | T58: - | U58: -4 | V58: - | W58: -158 | X58: -4709 | Y58: -5102 | Z58: -493 | AA58: - | AB58: - | AC58: -846 | AD58: -1 | AE58: - | AF58: - | AG58: - | AH58: - | AI58: - | AJ58: - | AK58: - | AL58: -
D59: Dividend paid to non-controlling interests | E59: - | F59: - | G59: - | H59: - | I59: - | J59: - | K59: - | L59: - | M59: - | N59: - | O59: - | P59: - | Q59: - | S59: - | T59: - | U59: - | V59: - | W59: - | X59: - | Y59: - | Z59: - | AA59: - | AB59: - | AC59: - | AD59: - | AE59: - | AF59: - | AG59: - | AH59: - | AI59: - | AJ59: - | AK59: - | AL59: -
D60: Received shareholders’ contribution | E60: - | F60: 293 | G60: 1555 | H60: 3992 | I60: - | J60: - | K60: - | L60: - | M60: - | N60: 360 | O60: - | P60: - | Q60: - | S60: - | T60: - | U60: - | V60: - | W60: - | X60: - | Y60: 360 | Z60: - | AA60: - | AB60: - | AC60: - | AD60: - | AE60: - | AF60: - | AG60: - | AH60: - | AI60: - | AJ60: - | AK60: - | AL60: -
D61: Investments in marketable securities, net | E61: - | F61: -88 | G61: -978 | H61: -2488 | I61: -1189 | J61: 785 | K61: 2558 | L61: -1985 | M61: - | N61: - | O61: - | P61: - | Q61: - | S61: - | T61: - | U61: - | V61: - | W61: - | X61: - | Y61: - | Z61: - | AA61: - | AB61: - | AC61: - | AD61: - | AE61: - | AF61: - | AG61: - | AH61: - | AI61: - | AJ61: - | AK61: - | AL61: -
D62: Investments in marketable securities | E62: - | F62: - | G62: - | H62: - | I62: - | J62: - | K62: - | L62: - | M62: -8806 | N62: -15015 | O62: -21127 | P62: -10792 | Q62: - | S62: -524 | T62: - | U62: - | V62: -8282 | W62: -4682 | X62: -1745 | Y62: -1653 | Z62: -6935 | AA62: -9256 | AB62: -2227 | AC62: -3899 | AD62: -5745 | AE62: -360 | AF62: - | AG62: -335 | AH62: -10097 | AI62: - | AJ62: - | AK62: - | AL62: -
D63: Matured marketable securities | E63: - | F63: - | G63: - | H63: - | I63: - | J63: - | K63: - | L63: - | M63: 4114 | N63: 15475 | O63: 26157 | P63: 4115 | Q63: 10269 | S63: 1147 | T63: 2442 | U63: 524 | V63: 1 | W63: 4943 | X63: 4615 | Y63: 1853 | Z63: 4064 | AA63: 10074 | AB63: 2555 | AC63: 2294 | AD63: 11234 | AE63: 3781 | AF63: - | AG63: 335 | AH63: -1 | AI63: 288 | AJ63: 5938 | AK63: 3474 | AL63: 569
D64: Other | E64: -356 | F64: 181 | G64: 895 | H64: 632 | I64: 361 | J64: 271 | K64: 1033 | L64: 112 | M64: -396 | N64: 905 | O64: 726 | P64: 376 | Q64: -368 | S64: 418 | T64: -267 | U64: -185 | V64: -362 | W64: -271 | X64: 198 | Y64: 658 | Z64: 320 | AA64: 28 | AB64: 460 | AC64: -149 | AD64: 388 | AE64: 638 | AF64: 186 | AG64: 232 | AH64: -680 | AI64: -140 | AJ64: -176 | AK64: 692 | AL64: -744
D65: Cash flow from financing activities | E65: 456 | F65: 5677 | G65: 3641 | H65: 1445 | I65: 5792 | J65: 1333 | K65: -743 | L65: -831 | M65: =SUM(M49:M64) -> -834 | N65: 1178 | O65: =SUM(O50:O64) -> 3929 | P65: -5251 | Q65: 5916 | S65: 741 | T65: 3446 | U65: -241 | V65: -4780 | W65: -620 | X65: -6837 | Y65: -3609 | Z65: 12244 | AA65: 500 | AB65: 2326 | AC65: -2981 | AD65: 5124 | AE65: 3906 | AF65: 195 | AG65: -213 | AH65: -9139 | AI65: -344 | AJ65: 3814 | AK65: 3364 | AL65: -918
D66: Cash flow for the period | E66: -4473 | F66: 5786 | G66: -1125 | H66: 8679 | I66: 12307 | J66: -2467 | K66: 3962 | L66: 10742 | M66: =+M46+M65 -> 12448 | N66: -3707 | O66: -1090 | P66: -14226 | Q66: 7043 | S66: -14653 | T66: 6037 | U66: 9907 | V66: 11157 | W66: -7510 | X66: -6846 | Y66: -12836 | Z66: 23485 | AA66: -11772 | AB66: -3274 | AC66: 256 | AD66: 13700 | AE66: -13543 | AF66: 879 | AG66: 1516 | AH66: -3078 | AI66: -12545 | AJ66: 3933 | AK66: 2963 | AL66: 12692
D68: Cash and cash equivalents at beginning of the year | E68: 14634 | F68: 9607 | G68: 17533 | H68: 17002 | I68: 25623 | J68: 38635 | K68: 35402 | L68: 40170 | M68: 51997 | N68: 61592 | O68: 62265 | P68: 63743 | Q68: 47861 | S68: 51997 | T68: 38885 | U68: 43288 | V68: 53071.671 | W68: 61592 | X68: 56211 | Y68: 48450 | Z68: 36403 | AA68: 62265 | AB68: 51418 | AC68: 50035 | AD68: 50348 | AE68: 63743 | AF68: 50323 | AG68: 51701 | AH68: 52766 | AI68: 47861 | AJ68: 36053 | AK68: 39911 | AL68: 42965
D69: Exchange difference on cash and cash equivalents | E69: -554 | F69: -21 | G69: 594 | H69: -58 | I69: 705 | J69: -766 | K69: 806 | L69: 1085 | M69: -2853 | N69: 4380 | O69: 2568 | P69: -1656 | Q69: 1469 | S69: 1541 | T69: -1634 | U69: -216 | V69: -2544 | W69: 2129 | X69: -915 | Y69: 789 | Z69: 2377 | AA69: 925 | AB69: 1891 | AC69: 57 | AD69: -305 | AE69: 123 | AF69: 499 | AG69: -451 | AH69: -1827 | AI69: 737 | AJ69: -75 | AK69: 91 | AL69: 716
D70: Cash and cash equivalents at end of the year | E70: 9607 | F70: 15372 | G70: 17002 | H70: 25623 | I70: 38635 | J70: 35402 | K70: 40170 | L70: 51997 | M70: =+M66+M68+M69 -> 61592 | N70: 62265 | O70: 63743 | P70: 47861 | Q70: 56373 | S70: 38885 | T70: 43288 | U70: 53071.671 | V70: 61592 | W70: 56211 | X70: 48450 | Y70: 36403 | Z70: 62265 | AA70: 51418 | AB70: 50035 | AC70: 50348 | AD70: 63743 | AE70: 50323 | AF70: 51701 | AG70: 52766 | AH70: 47861 | AI70: 36053 | AJ70: 39911 | AK70: 42965 | AL70: 56373
D73: 1) Not restated after the acquisitions of the Chinese industrial entities in 2015.
D74: 2) The comparative figures for 2014 are restated to include the new Volvo Car Group structure including the acquired Chinese industrial entities. For further descriptions refer to the Volvo Car Group’s annual report 2015.
D75: 3) In 2021, Investment in shares and participations have been reported in gross, adding Capital repayments from shares in participations. Investment in marketable securities have also been reported in gross, adding Matured marketable securities. The comparable figures for 2020 have been adjusted accordingly.
D76: 4) In 2021, Dividends received from joint ventures and associates have been reclassified from Investing activities to Operating activities. Comparative figures for 2020 have been adjusted accordingly.
D77: 5) In 2021, renamed Property, plant and equipment to Tangible assets.
D78: 6) In 2022, a prior period error was identified with regards to the recognition of a government grant in China. The comparative figures have been adjusted accordingly affecting 2020.
